Workbook

Sheet Questions
A1: ID | B1: Year | C1: Series | D1: Paper | E1: Section | F1: Q | G1: Part | H1: Choice | I1: Marks | J1: AO3 marks | K1: Command word | L1: 2nd command | M1: Diagram | N1: Calc | O1: Stem patterns | P1: Primary topic | Q1: Primary topic name | R1: All topics | S1: Sub-topics | T1: Key concepts | U1: Context (data response) | V1: Question | W1: Mark scheme | X1: MS page | Y1: QP page | Z1: Question text from | AA1: Flags | AB1: Reviewed? | AC1: Reviewer notes | AD1: Similar question in another paper | AE1: Examiner report comment
A2: 9708_m21_22_Q1a | B2: 2021 | C2: Feb/March | D2: 9708/22 | E2: A | F2: 1 | G2: a | I2: 1 | J2: 0 | K2: Calculate | N2: Yes | O2: uses data | P2: 4.6 | Q2: Price stability | R2: ;4.6; | S2: 4.6.2 | T2: inflation rate, price index, data calculation | U2: Japan – deflation and monetary policy | V2: Calculate the rate of inflation in Japan from 2014 to the estimate in 2019. | W2: 2.6% (1) | X2: 8 | Y2: 3 | Z2: question paper | AA2: Needs data removed from the published paper (copyright): the table/figure this part refers to is not in the public copy. | AD2: 9708_s22_22_Q1ai (61%) | AE2: This was a straightforward calculation question. A significant number of candidates were unable to correctly calculate the percentage change and simply subtracted figures which in this instance did give the correct figure but this was due to the closeness of the figures. Candidates do need to know and understand the correct formula for calculating percentage changes.
A3: 9708_m21_22_Q1b | B3: 2021 | C3: Feb/March | D3: 9708/22 | E3: A | F3: 1 | G3: b | I3: 1 | J3: 0 | K3: Identify | P3: 5.2 | Q3: Fiscal policy | R3: ;5.2; | S3: 5.2.6 | T3: fiscal stance, budget deficit, data interpretation | U3: Japan – deflation and monetary policy | V3: With reference to Table 1.1 identify one piece of evidence that suggests that Japan has not been using an expansionary fiscal policy before 2019. | W3: Government expenditure as a % of aggregate expenditure is falling over the period or is not increasing. (1) OR Budget deficit as a % of aggregate expenditure is falling over the period. (1) | X3: 8 | Y3: 3 | Z3: question paper | AA3: Needs data removed from the published paper (copyright): the table/figure this part refers to is not in the public copy. | AE3: This was another straightforward question that required candidates to understand that expansionary fiscal policy would be likely to increase government expenditure as a percentage of aggregate expenditure and/or the budget deficit would be likely to increase. The fact that both were falling suggested Japan was not using an expansionary fiscal policy. Most candidates understood this and gained the mark, but a number did not understand the significance of these indicators.
A4: 9708_m21_22_Q1c | B4: 2021 | C4: Feb/March | D4: 9708/22 | E4: A | F4: 1 | G4: c | I4: 2 | J4: 0 | K4: Explain | P4: 4.6 | Q4: Price stability | R4: ;4.6; | S4: 4.6.1, 4.6.5 | T4: deflation, consumption, delayed spending | U4: Japan – deflation and monetary policy | V4: Explain why deflation, as experienced by Japan, discourages consumption spending. | W4: For a clear understanding that deflation refers to a fall in the general price level (1) For explaining why, a fall in the general price level will discourage consumption. (1) (Up to 2 marks) Guidance: Consumption is discouraged because as the expectations of price falls takes hold consumers hold back purchases because they expect prices to fall in the future. Also, the general air of uncertainty encourages consumers to save for the future. | X4: 8 | Y4: 3 | Z4: question paper | AA4: Section A source partly removed for copyright; this part can still be attempted from general knowledge. | AE4: This was generally well answered provided candidates understood what was meant by deflation. Some confused it with disinflation which is clearly not the same and some adopted a micro approach and focused on specific products. Provided the candidate clearly understood the meaning of deflation and the likely consequences of deferred purchases and/or increased uncertainty, the full 2 marks were easily gained.
A5: 9708_m21_22_Q1d | B5: 2021 | C5: Feb/March | D5: 9708/22 | E5: A | F5: 1 | G5: d | I5: 4 | J5: 0 | K5: Explain | M5: Yes | O5: diagram required | P5: 6.4 | Q5: Exchange rates | R5: ;6.4;5.3; | S5: 6.4.2, 6.4.4 | T5: exchange rate, interest rate differentials, depreciation | U5: Japan – deflation and monetary policy | V5: Use a diagram to explain what you would expect to happen to the Yen : US dollar exchange rate if the Bank of Japan continued with low interest rates, ‘even as other central banks around the world begin raising rates’. | W5: For a diagram that shows either an increased supply of yen onto the forex market (1) as interest rates rise abroad and the change in the price of the yen and quantity traded (1) or a decrease in the demand for the yen on the forex market (1) as interest rates rise abroad and the change in the price of the yen and quantity traded (1) (Up to 2 marks) For an accompanying explanation of reason for the shift shown (either an increased supply of yen or reduced demand for yen) (1) and a conclusion that it would be expected that the yen would depreciate (or fall) (1) (Up to 2 marks) Guidance: The diagram should be correctly labelled and show a change in the exchange rate and a change in the quantity traded. There must be some accompanying explanation for full marks. | X5: 9 | Y5: 3 | Z5: question paper | AA5: Quotes source text removed from the published paper (copyright); answerable only in general terms from this copy. | AE5: This question was not particularly well answered by many candidates. The question asked for a diagram to show either an increase in supply of the Yen or a fall in demand of the Yen to illustrate an expected depreciation of the Yen against the US$. Unfortunately, diagrams were often inaccurate and/or labelled incorrectly and therefore did not show the correct movement in the value of the Yen. Obviously, the best answers occurred when candidates understood why the supply and/or demand for the Yen would change in this way as money flowed out of Japan and were able to illustrate this diagrammatically to come to a logical conclusion. For many, this area of the syllabus continues to cause some confusion.
A6: 9708_m21_22_Q1e | B6: 2021 | C6: Feb/March | D6: 9708/22 | E6: A | F6: 1 | G6: e | I6: 6 | J6: 2 | K6: Discuss | L6: Consider | P6: 5.3 | Q6: Monetary policy | R6: ;5.3;4.6;4.3; | S6: 5.3.3, 5.3.4, 4.6.4 | T6: expansionary monetary policy, deflation, aggregate demand | U6: Japan – deflation and monetary policy | V6: Discuss how continuing with an expansionary monetary policy is expected to boost inflation and consider whether it is likely to be successful. | W6: For clear understanding of the meaning of expansionary monetary policy. (1) For an explanation of how this might stimulate aggregate demand and ‘boost inflation’ (Up to 2 marks for each component of aggregate demand that is considered) (Up to 3 marks) For evaluative comment on whether this is likely to be successful. (Up to 2 marks) Guidance: An expansionary monetary policy means cutting interest rates and/or increasing the money supply. We allow quantitative easing as expansionary monetary policy. It is expected that this will stimulate investment and/ or consumption and this will stimulate aggregate demand and might increase prices. It might also lead to a fall in the exchange rate and an increase in net exports. This might not work for a number of reasons. For example, investment might be unresponsive to interest rate changes. The table also shows that despite loose monetary policy over the period, investment has stayed relatively stable. This could contribute to a conclusion. | X6: 10 | Y6: 3 | Z6: question paper | AA6: Section A source partly removed for copyright; this part can still be attempted from general knowledge. | AE6: Most candidates demonstrated an understanding of what is meant by expansionary monetary policy although there was occasional confusion with fiscal policy. Most candidates then focused on consumption rather than investment or net exports and consequently analysis was often undeveloped and/or assertive. Consequently, evaluation was often weak or missing altogether and based on an assertion that AD and therefore prices would rise as a result rather than examining reasons why they might not.
A7: 9708_m21_22_Q1f | B7: 2021 | C7: Feb/March | D7: 9708/22 | E7: A | F7: 1 | G7: f | I7: 6 | J7: 2 | K7: Discuss | P7: 5.2 | Q7: Fiscal policy | R7: ;5.2;4.3;6.3; | S7: 5.2.6, 5.2.7, 4.3.5 | T7: government spending, expansionary fiscal policy, external demand | U7: Japan – deflation and monetary policy | V7: Discuss whether increases in government spending can offset risks to Japan’s economy if a downturn in foreign economies occurs. | W7: For an explanation of the risks to Japan’s economy if a downturn in foreign economies occurs. (Up to 1 mark) For an explanation of how fiscal policy could be used to offset risks to the economy of Japan (Up to 3 marks) For evaluative comment that reaches a reasoned conclusion (2 marks) Guidance: If there is a downturn in foreign economies Japan would experience falling exports and this would decrease aggregate demand. This would result in falling incomes and unemployment. Increased government spending could be adopted to boost domestic demand if world trade falls. It could also be used to offset the impact upon consumption of the sales tax rise that is planned in October. | X7: 10 | Y7: 3 | Z7: question paper | AA7: Section A source partly removed for copyright; this part can still be attempted from general knowledge. | AE7: Most candidates gained some marks on this question which basically asked whether the impact of a fall in exports on AD and therefore, e.g. unemployment could be offset by an increase in government spending. Candidates who gained higher marks were able to fully explain the points they made and arrive at a reasoned conclusion. Weaker answers tended to make assertive points, i.e. without explanation and lacked any reasoned judgements. Some candidates did ignore the reference to the risks of a downturn in foreign economies and merely discussed the impact of an increase in government spending which failed to answer the question. Section B Essays
A8: 9708_m21_22_Q2a | B8: 2021 | C8: Feb/March | D8: 9708/22 | E8: B | F8: 2 | G8: a | H8: One of 2, 3 or 4 | I8: 8 | J8: 0 | K8: Explain | M8: Yes | O8: diagram required | P8: 1.5 | Q8: Production possibility curves | R8: ;1.5;1.3; | S8: 1.5.3, 1.5.4, 1.3.1 | T8: PPC, unused labour, natural resources, PPC shift | V8: Use production possibility curve (PPC) diagrams to explain the effect on an economy’s output of (i) increased use of its existing labour, and (ii) an increased availability of natural resources. | W8: For knowledge and understanding of a production possibility curve and application to show an increased use of its existing labour. For a diagram of a PPC with appropriately labelled axes (1) showing a movement from a point within a PPC to a point on or nearer to the PPC curve (1) For an explanation of how an improved utilisation of resources results in the change shown (Up to 2 marks) (Up to 4 marks) For knowledge and understanding of a production possibility curve and application to show an increased availability of natural resources. For a diagram of a PPC with appropriately labelled axes (1) showing a shift outward of the curve (1) For an explanation of how an increased availability of natural resources results in the change shown (Up to 2 marks) (Up to 4 marks) Guidance: An increased use of existing labour will lead to a fall in unemployment, and this will result in increased total output as the point within the curve moves closer to the production frontier. There is improved utilisation of labour resources. An increased availability of natural resources will increase the potential output of the economy. It is also likely that total output will rise. | X8: 11 | Y8: 4 | Z8: question paper | AE8: This question required candidates to distinguish between a movement from a point within the PPC as a result of an increased use of existing labour and a shift outward of the PPC due to an increased availability of existing resources. Many candidates were able to gain some credit via correct diagrams, but explanations were often partial and tended to ignore any reference to the impact on an economy’s output. Some candidates thought both scenarios would lead to the same outcome, normally an outward shift and there were a number who incorrectly labelled diagrams as P and Q.
A9: 9708_m21_22_Q2b | B9: 2021 | C9: Feb/March | D9: 9708/22 | E9: B | F9: 2 | G9: b | H9: One of 2, 3 or 4 | I9: 12 | J9: 4 | K9: Discuss | P9: 5.4 | Q9: Supply-side policy | R9: ;5.4;1.3; | S9: 5.4.3, 1.3.1 | T9: supply-side policy, labour supply, enterprise | V9: Discuss the view that supply side policies to increase the supply of labour to an economy are likely to be more successful than those designed to increase the supply of entrepreneurship. | W9: For analysis of at least two supply side measures that are designed to increase the supply of labour to an economy. If only one measure considered then 3 maximum (Up to 4 marks) For analysis of at least two supply side measures that are designed to increase the supply of entrepreneurship to the economy. If only one measure considered then 3 maximum (Up to 4 marks) For evaluative comment on which policies are likely to be successful (3) that reaches a reasoned conclusion (1) Guidance: Supply of labour: Training to enter the labour force, relaxation of immigration controls, reduction of income taxes, raising of the retirement age etc. Supply of entrepreneurship: Training in management skills, reduction in business taxes, subsidies, start-up grants etc | X9: 12 | Y9: 4 | Z9: question paper | AE9: This question was slightly different to previous questions about supply side policy as it focused on increasing the supply of two factors of production, labour, and entrepreneurship, rather than the output of the economy. This clearly confused a number of candidates who seemed to fail to recognise this and simply discussed the possible success of supply side policy in general. Consequently, good answers were rare and where the question was correctly addressed, most answers focused on training and education rather than other possible policies such as fiscal policies such as taxes and grants. The important point to make is that it is important to read questions carefully.
A10: 9708_m21_22_Q3a | B10: 2021 | C10: Feb/March | D10: 9708/22 | E10: B | F10: 3 | G10: a | H10: One of 2, 3 or 4 | I10: 8 | J10: 0 | K10: Explain | P10: 2.2 | Q10: PED, YED and XED | R10: ;2.2; | S10: 2.2.1, 2.2.3 | T10: XED, complements, substitutes, cars | V10: Explain how you would use the concept of cross-elasticity of demand to measure the impact on the demand for cars when there is a rise in the price of fuel for cars and when there is a rise in the price of public transport. | W10: For knowledge and understanding of cross elasticity of demand. What it measures (1) Formula (1) (Up to 2 marks) For application using the concept to explain the impact of a rise in the price of petrol on the demand for cars • For stating that since cars and fuel are complements the coefficient will be negative (1) • For explaining why a negative coefficient will result when there is a rise in the price of fuel (1) • For explaining that the impact will be greater and the coefficient will be higher the closer the relationship (1) (Up to 3 marks) For application using the concept to explain the impact of a rise in the price of public transport on the demand for cars • For stating that since cars and public transport are substitutes the coefficient will be positive (1) • For explaining why a positive coefficient will result when there is a rise in the price of public transport (1) • For explaining that the impact will be greater and the coefficient will be higher the closer the relationship (1) (Up to 3 marks) | X10: 13 | Y10: 4 | Z10: question paper | AE10: This was a popular question and generally was answered quite well. Most candidates were able to explain cross-elasticity of demand and apply it to the demand for cars in the two scenarios of a rise in the price of fuel and a rise in the price of public transport. The better answers were differentiated by a closer examination of the size of the coefficient and not just whether it would be negative or positive. For future questions of this nature, candidates should be advised not just to consider whether goods are complements or substitutes, but also the strength of the relationship based on the value of the coefficient.
A11: 9708_m21_22_Q3b | B11: 2021 | C11: Feb/March | D11: 9708/22 | E11: B | F11: 3 | G11: b | H11: One of 2, 3 or 4 | I11: 12 | J11: 4 | K11: Discuss | P11: 6.2 | Q11: Protectionism | R11: ;6.2; | S11: 6.2.2, 6.2.3 | T11: import controls, protectionism, car industry, retaliation | V11: A government is deciding whether to impose import controls to protect its car manufacturing industry. Discuss the factors that should be considered in this decision, and whether these import controls can be justified. | W11: For analysis of the possible reasons for protection of the car industry (Up to 4 marks) For analysis of the factors that should be considered (Up to 4 marks) (8 marks maximum) For evaluative comment (Up to 3 marks) and 1 mark for a conclusion Guidance: Possible reasons include: to save jobs, protect infant industries, prevent dumping, protect the current account of the balance of payments etc. Factors that should be considered include: whether the industries are really infant industries, whether the charge of dumping can be justified etc. | X11: 14 | Y11: 4 | Z11: question paper | AE11: The question concerned protection of a country’s car manufacturing industry and whether such protection could ever be justified through import controls. Most responses answered the question in general terms rather than with specific reference to car manufacturing and were generally stronger in terms of the reasons why protectionism may be justified. Some candidates focused on descriptions of the tools of protection which was not the question. Strong analysis which considered the strengths and weaknesses of both sides of the argument was rare and as such evaluation was often missing or very limited. As referred to in the Key messages and General comments, candidates need to be encouraged to explain arguments rather than make assertions and attempt to bring together the various arguments when attempting to make evaluative judgements.
A12: 9708_m21_22_Q4a | B12: 2021 | C12: Feb/March | D12: 9708/22 | E12: B | F12: 4 | G12: a | H12: One of 2, 3 or 4 | I12: 8 | J12: 0 | K12: Explain | P12: 2.4 | Q12: The interaction of demand and supply | R12: ;2.4;2.1; | S12: 2.4.1, 2.4.2, 2.1.6 | T12: market equilibrium, wages, costs of production, income effect on demand | V12: Explain what is meant by equilibrium price and quantity in the market for a good and how price and quantity will be affected by both a rise in the wage rate paid to the workers producing the good and a rise in wages paid to all workers in the economy. | W12: For knowledge and understanding of the meaning of equilibrium price and quantity. • For knowledge that this occurs in a market where supply is equal to demand (1) • For understanding that equilibrium price and quantity is when there is no tendency to change (1) (Up to 2 marks) For application showing the impact of a rise in the wage rate • For a diagram (or explanation) showing a shift in the supply curve to the left (1) • For an explanation of why this will occur in terms of the rise in costs (1) • For explaining (or illustrating) that the equilibrium price will rise and the equilibrium quantity will fall (1) (Up to 3 marks) For application showing the impact of a rise in the wages in the economy in terms of a shift in the demand curve to the right • For a diagram (or explanation) showing a shift in the demand curve to the right (or left in the case of an inferior good) (1) • For an explanation of why this will occur in terms of the rise in incomes (1) Guidance: • For explaining (or illustrating) the change in the equilibrium price and the equilibrium quantity depending upon the type of good chosen (1) (Up to 3 marks) (8 marks maximum) | X12: 15 | Y12: 4 | Z12: question paper | AE12: Most candidates were able to explain that equilibrium occurs in a market when supply equals demand but did not elaborate this to further explain that this meant that there is no tendency to change. This meant they did not gain the full two marks available for knowledge and understanding. Most candidates were, however, able to distinguish between the effects causing an increase in costs for a good due to an increase in wage costs and an increase in demand (or fall depending on the nature of the good) because of wages for all workers rising. Consequently, there were some pleasing answers. Weaker responses tended to focus on the increase in supply costs and suggested an increase in AS rather than an individual firm’s supply and ignored any impact on demand for its product or suggested that AD would be affected.
A13: 9708_m21_22_Q4b | B13: 2021 | C13: Feb/March | D13: 9708/22 | E13: B | F13: 4 | G13: b | H13: One of 2, 3 or 4 | I13: 12 | J13: 4 | K13: Discuss | P13: 3.2 | Q13: Methods and effects of government intervention in markets | R13: ;3.2;3.1; | S13: 3.2.1, 3.2.2, 3.2.4, 3.1.1 | T13: government intervention, price controls, taxes and subsidies, resource allocation | V13: Discuss whether government policies to influence the free market price for a good can ever improve the allocation of resources in that market. | W13: For analysis of at least two policies to influence the free market price for a good. If only one measure considered then 3 maximum. (Up to 4 marks) For analysis that considers the advantages and disadvantages of using these policies. (Up to 4 marks) For evaluative comment on whether the policies ‘can ever improve’ the allocation of resources (Up to 3 marks) and 1 mark for a conclusion Guidance: Policies include maximum and minimum prices, indirect taxes, subsidies, information campaigns etc. The advantages and disadvantages must relate to the policies chosen. For example, maximum prices might lead to shortages, subsidies might be very expensive as might information campaigns. | X13: 16 | Y13: 4 | Z13: question paper | AE13: Most candidates focused on policies such as minimum prices and/or maximum prices although subsidies were occasionally referred to. Once again, there was a tendency to explain the mechanics of the policies rather than directly addressing the question of whether the policies could ever improve the allocation of resources in a market. It is important to note that simply displaying knowledge and understanding of, e.g. a concept is not analysis. It requires some assessment of its usefulness, e.g. via an explanation of strengths and weaknesses in the context of the question. Such an approach leads to a more meaningful judgement and conclusion whereas simply demonstrating knowledge and understanding invariably leads to unjustified assertions, The difference between these two approaches distinguishes between higher and lower marks. 9708 Economics February/March 2021
A14: 9708_s21_21_Q1ai | B14: 2021 | C14: May/June | D14: 9708/21 | E14: A | F14: 1 | G14: a(i) | I14: 1 | J14: 0 | K14: Describe | P14: 6.3 | Q14: Current account of the balance of payments | R14: ;6.3; | S14: 6.3.2 | T14: current account balance, data trend | U14: Vietnam – fruit and vegetable exports to China | V14: Describe the overall trend in Vietnam’s current account balance between Q1 2017 and Q2 2018. | W14: A deficit at the beginning of the period, followed by surpluses OR Generally increasing/improving balance over the period (one exception) (1 mark) | X14: 6 | Y14: 3 | Z14: question paper | AD14: 9708_m22_22_Q1a (59%), 9708_s24_21_Q1ai (56%)
A15: 9708_s21_21_Q1aii | B15: 2021 | C15: May/June | D15: 9708/21 | E15: A | F15: 1 | G15: a(ii) | I15: 1 | J15: 0 | K15: Calculate | N15: Yes | O15: uses data | P15: 6.3 | Q15: Current account of the balance of payments | R15: ;6.3; | S15: 6.3.2 | T15: exports, data calculation | U15: Vietnam – fruit and vegetable exports to China | V15: Calculate the value of Vietnam’s exports of fruit and vegetables to China in the first four months of 2018. | W15: US$1 billion (US$1.001 billion) (1 mark) Guidance: (Line one gives the total as US$1.3bn and the fourth paragraph says that China accounts for 77% of this.) Candidates do need to refer to billion, but not necessarily to US$ | X15: 6 | Y15: 3 | Z15: question paper
A16: 9708_s21_21_Q1b | B16: 2021 | C16: May/June | D16: 9708/21 | E16: A | F16: 1 | G16: b | I16: 4 | J16: 0 | K16: Explain | P16: 2.4 | Q16: The interaction of demand and supply | R16: ;2.4;2.1; | S16: 2.1.3, 2.1.4, 2.4.2 | T16: determinants of demand, determinants of supply, exports | U16: Vietnam – fruit and vegetable exports to China | V16: Explain one possible demand factor and one possible supply factor that could have caused the increase in Vietnam’s export sales of fruit and vegetables. | W16: For an explanation of one possible demand reason (Up to 2 marks) (1 mark for identification, 1 mark for further development) For an explanation of a one possible supply reason (Up to 2 marks) (1 mark for identification, 1 mark for further development) Guidance: Demand factors could include: • increase in income • more effective advertising • population growth • tastes have changed in favour of the products, e.g. healthy living Supply factors could include: • use of more land • more favourable weather conditions • reduction in costs of production • improved technology | X16: 6 | Y16: 3 | Z16: question paper | AD16: 9708_s22_23_Q1bii (61%)
A17: 9708_s21_21_Q1c | B17: 2021 | C17: May/June | D17: 9708/21 | E17: A | F17: 1 | G17: c | I17: 2 | J17: 0 | K17: Explain | P17: 2.1 | Q17: Demand and supply curves | R17: ;2.1;6.2; | S17: 2.1.6, 6.2.2 | T17: administrative barriers, costs of production, supply shift | U17: Vietnam – fruit and vegetable exports to China | V17: Explain how complying with administrative burdens on trade will affect Vietnam’s supply of fruit and vegetables for export. | W17: Higher costs of production will shift supply to the left and decrease the amount available to export. (Up to 2 marks) Guidance: Possible effects could include: • fruit and vegetable exporters could face additional costs in satisfying administrative burdens on trade • these could include strict hygiene and food safety regulations • this could bring about an increase in the price of the products • regulations could, however, lead to a higher quality of products being supplied | X17: 7 | Y17: 3 | Z17: question paper
A18: 9708_s21_21_Q1d | B18: 2021 | C18: May/June | D18: 9708/21 | E18: A | F18: 1 | G18: d | I18: 6 | J18: 1 | K18: Discuss | P18: 6.1 | Q18: The reasons for international trade | R18: ;6.1;6.3; | S18: 6.1.2, 6.1.4, 6.3.3 | T18: dependence on one export market, specialisation, risk | U18: Vietnam – fruit and vegetable exports to China | V18: Discuss whether the risks of Vietnam relying very heavily on the Chinese market for the export of its fruit and vegetables are greater than the potential benefits. | W18: For an explanation of the potential risks. (Up to 3 marks) For an explanation of the potential benefits. (Up to 3 marks) Reserve 1 mark for a conclusion Guidance: Potential risks of the Chinese market: • high proportion of trade in fruit and vegetables with China may mean that Vietnam is neglecting other potential trading contacts • very large gap from China (77%) to second country (US with 2.84%) and third country (Japan with 2.70%) • external shocks, or changes in the Chinese economy, such as a recession, would have a large impact on Vietnam’s fruit and vegetables industry Potential benefits of the Chinese market: • with 77% of the trade in fruit and vegetables with China, close trading contacts would have been established • security of trade in fruit and vegetables resulting from these trading contacts • with established customers, discounts could be negotiated to secure future trade | X18: 7 | Y18: 3 | Z18: question paper
A19: 9708_s21_21_Q1e | B19: 2021 | C19: May/June | D19: 9708/21 | E19: A | F19: 1 | G19: e | I19: 6 | J19: 1 | K19: Discuss | P19: 4.3 | Q19: AD and AS analysis | R19: ;4.3;6.3; | S19: 4.3.5, 4.3.12 | T19: net exports, aggregate demand, AD/AS, inflation | U19: Vietnam – fruit and vegetable exports to China | V19: Using aggregate demand and aggregate supply analysis, discuss the possible impact on Vietnam’s economy of a sustained increase in its net exports. | W19: For an explanation of the potential advantages of a sustained increase in net exports using AD/AS analysis. (Up to 3 marks) For an explanation of the potential disadvantages of a sustained increase in net exports using AD/AS analysis. (Up to 3 marks) Reserve 1 mark for a conclusion Guidance: Potential advantages: • increase in exports would contribute positively to Vietnam’s current account balance • increase in aggregate demand • increase in incomes and employment Potential disadvantages: • increase in exports could mean less is available for the domestic market • could impact on the rate of domestic inflation | X19: 8 | Y19: 3 | Z19: question paper
A20: 9708_s21_21_Q2a | B20: 2021 | C20: May/June | D20: 9708/21 | E20: B | F20: 2 | G20: a | H20: One of 2, 3 or 4 | I20: 8 | J20: 0 | K20: Explain | P20: 1.6 | Q20: Classification of goods and services | R20: ;1.6;1.4; | S20: 1.6.1, 1.6.2, 1.4.2 | T20: private goods, free goods, public goods, market economy | V20: Explain whether private goods, free goods and public goods will all be sold in a free market economy. | W20: For Knowledge and Understanding For knowledge and understanding of private goods, free goods and public goods. Up to 2 marks) For knowledge and understanding of just two types of good. (Up to 1 mark) 2 marks maximum For Application Explanation of the market mechanism in relation to the three types of good Up to 2 marks for an explanation of each type of good) 6 marks maximum Guidance: Free goods are not sold in a free market economy: • are not scarce and so do not have a market price attached to them • the supply equals the demand at zero price • have no property rights associated with them • require no factors of production for their enjoyment Private goods are sold in a free market economy: • economic goods that are consumed by an individual for their own benefit • there is rivalry in consumption, i.e. when a product is consumed by one person, it cannot be consumed by another • there is excludability in consumption, i.e. when a product is consumed by one person, all others are excluded from it Public goods are not sold in a free market economy: • are non-rival • are non-excludable • are non-rejectable Examples of free goods: air, sunshine Examples of private goods: most products in an economy, such as food and clothing; can include examples of merit goods/demerit goods Examples of public goods: street lighting, defence and police | X20: 9 | Y20: 3 | Z20: question paper | AD20: 9708_w23_22_Q3a (55%)
A21: 9708_s21_21_Q2b | B21: 2021 | C21: May/June | D21: 9708/21 | E21: B | F21: 2 | G21: b | H21: One of 2, 3 or 4 | I21: 12 | J21: 4 | K21: Discuss | P21: 3.2 | Q21: Methods and effects of government intervention in markets | R21: ;3.2;2.4;1.4; | S21: 3.2.3, 2.4.4 | T21: direct provision, price mechanism, resource allocation | V21: Discuss whether the direct provision of goods and services by the government prevents the price mechanism from working effectively. | W21: For Analysis Analysis of the prevention of the price mechanism from working effectively. (Up to 4 marks) Analysis of the potential fact that it does not prevent the price mechanism from working effectively. (Up to 4 marks) 8 marks maximum For Evaluation For exercising some judgement on whether the direct provision of goods and services by the government prevents the price mechanism from working effectively. (Up to 4 marks) Reserve 1 mark for a conclusion 4 marks maximum Guidance: The effect of direct provision of goods and services by the government: • does it prevent the price mechanism from rationing? • does it prevent the price mechanism from signalling? • does it prevent the price mechanism from transmitting preferences? The direct provision of goods and services by the government will be financed through the tax system, e.g. education and health care, and so will not be allocated through a price mechanism. However, education and health care can also be provided through a price mechanism and in this situation the mechanism can function as a rationing and signalling device and as a way of transmitting preferences | X21: 10 | Y21: 3 | Z21: question paper
A22: 9708_s21_21_Q3a | B22: 2021 | C22: May/June | D22: 9708/21 | E22: B | F22: 3 | G22: a | H22: One of 2, 3 or 4 | I22: 8 | J22: 0 | K22: Explain | M22: Yes | O22: diagram required | P22: 2.5 | Q22: Consumer and producer surplus | R22: ;2.5;2.2; | S22: 2.5.1, 2.5.3, 2.2.6 | T22: consumer surplus, price fall, PED, luxury vs necessity | V22: With the aid of diagrams, explain how consumer surplus is affected by a decrease in the price of a luxury product with many substitutes, and of an essential product with few substitutes. | W22: For Knowledge and Understanding For correct diagram: Axes correctly labelled: P/Q (1 mark) Existence of consumer surplus (1 mark) 2 marks maximum For Application How consumer surplus is affected by a decrease in the price of a luxury product with many substitutes: elastic PED. (Up to 3 marks) How consumer surplus is affected by a decrease in the price of an essential product with few substitutes: inelastic PED’ (Up to 3 marks) 6 marks maximum Guidance: A decrease in the price of a product will increase the consumer surplus as more consumers are willing to pay the lower price. The extent of this will depend on the price elasticity of demand for a product. In the case of a luxury product with many substitutes, PED will be elastic. In the case of an essential product with few substitutes, PED will be inelastic. | X22: 11 | Y22: 3 | Z22: question paper
A23: 9708_s21_21_Q3b | B23: 2021 | C23: May/June | D23: 9708/21 | E23: B | F23: 3 | G23: b | H23: One of 2, 3 or 4 | I23: 12 | J23: 4 | K23: Discuss | O23: to what extent | P23: 2.2 | Q23: PED, YED and XED | R23: ;2.2; | S23: 2.2.8 | T23: YED, XED, business decisions | V23: Discuss the extent to which knowledge of the income elasticity of demand for its product is likely to be more useful to a business than knowledge of the cross elasticity of demand for its product. | W23: For Analysis Analysis of the usefulness of income elasticity of demand to a business, with the use of appropriate scenarios. (Up to 4 marks) Analysis of the usefulness of cross elasticity of demand to a business, with the use of appropriate scenarios. (Up to 4 marks) 8 marks maximum For Evaluation For exercising some judgement on whether knowledge of the income elasticity of demand for its product is likely to be more useful to a business than knowledge of the cross elasticity of demand for its product with regard to changes in the price of the products of other businesses. (Up to 4 marks) Reserve 1 mark for a conclusion 4 marks maximum Guidance: Income elasticity of demand can be useful to a business in relation to: • normal goods (positive YED) • inferior goods (negative YED) • economic development of a country • boom or recession: effect on business planning Cross elasticity of demand can be useful to a business in relation to: • substitutes/alternative demand (positive XED) • complements/joint demand (negative XED) | X23: 12 | Y23: 3 | Z23: question paper | AD23: 9708_w22_21_Q2b (56%), 9708_m24_22_Q3b (69%), 9708_w25_21_Q2b (64%), 9708_w25_22_Q2b (59%)
A24: 9708_s21_21_Q4a | B24: 2021 | C24: May/June | D24: 9708/21 | E24: B | F24: 4 | G24: a | H24: One of 2, 3 or 4 | I24: 8 | J24: 0 | K24: Explain | M24: Yes | O24: diagram required | P24: 6.4 | Q24: Exchange rates | R24: ;6.4; | S24: 6.4.2, 6.4.4 | T24: floating exchange rate, depreciation, currency demand and supply | V24: With the aid of a diagram(s), explain one demand factor and one supply factor that would cause the value of a currency in a floating exchange rate system to depreciate. | W24: For Knowledge and Understanding For correct diagram: Axes correctly labelled: P/Q of currency. (1 mark) (The vertical axis needs to make it clear that it is an exchange rate) Market equilibrium shown. (1 mark) 2 marks maximum For Application Explanation of one reason for a fall in demand (Up to 3 marks) (1 mark for identification of a relevant factor; up to 2 marks for a detailed explanation) Explanation of one reason for an increase in supply (Up to 3 marks) (1 mark for identification of a relevant factor; up to 2 marks for a detailed explanation) 6 marks maximum Guidance: A fall in demand for a currency could be caused by a: • the goods and services of a country are demanded less • a country’s interest rate is decreased An increase in the supply of a currency could be caused by: • an increase in interest rates in other countries • imported products are demanded more Note: the question specifically refers to the depreciation of an exchange rate | X24: 13 | Y24: 3 | Z24: question paper | AD24: 9708_w22_21_Q4a (62%), 9708_s23_21_Q5a (55%)
A25: 9708_s21_21_Q4b | B25: 2021 | C25: May/June | D25: 9708/21 | E25: B | F25: 4 | G25: b | H25: One of 2, 3 or 4 | I25: 12 | J25: 4 | K25: Discuss | P25: 5.3 | Q25: Monetary policy | R25: ;5.3;6.4;4.6; | S25: 5.3.4, 6.4.5, 4.6.4 | T25: monetary policy, inflation control, floating exchange rate, appreciation | V25: Discuss how likely it is that monetary policy would be successful in reducing inflation in an economy with a floating exchange rate. | W25: For analysis Analysis of the likely success of monetary policy in reducing inflation in an economy with a floating exchange rate (Up to 4 marks) Analysis of the likely difficulties of monetary policy in reducing inflation in an economy with a floating exchange rate. (Up to 4 marks) 8 marks maximum For evaluation For exercising some judgement on how likely it is that monetary policy would be successful in reducing inflation in an economy with a floating exchange rate. (Up to 4 marks) Reserve 1 mark for a conclusion 4 marks maximum Guidance: Monetary policy can be used to correct inflation in an economy by: • an increase in interest rates • a reduction in the money supply Cost-push inflation: an appreciation of a currency would lower import prices of finished products and raw materials/component parts Demand-pull inflation: an increase in interest rates and/or a decrease in the money supply would reduce aggregate demand and appreciate the currency Evaluation: appropriate reference to elasticities, the J-curve effect and the Marshall-Lerner condition | X25: 14 | Y25: 3 | Z25: question paper | AD25: 9708_w22_22_Q2b (58%), 9708_s23_21_Q4b (60%)
A26: 9708_s21_22_Q1a | B26: 2021 | C26: May/June | D26: 9708/22 | E26: A | F26: 1 | G26: a | I26: 2 | J26: 0 | K26: Compare | P26: 4.6 | Q26: Price stability | R26: ;4.6; | S26: 4.6.2 | T26: price level, data comparison | U26: Myanmar/Cambodia – EU tariffs on rice | V26: Compare the change in the price level in Myanmar with that in Cambodia between 2016 and 2018. | W26: Both price levels rose/both countries had inflation (1 mark) The price level rose by more in Myanmar / less in Cambodia / the rate of increase was increasing in Myanmar and declining in Cambodia / prices were increasing at a faster rate in Myanmar than in Cambodia/the change in the price level was more volatile in Myanmar (1 mark) Guidance: Do not credit answers that merely trawl through the data with no meaningful comparison If the candidate suggests that prices fell in Cambodia, 0 marks | X26: 6 | Y26: 3 | Z26: question paper
A27: 9708_s21_22_Q1b | B27: 2021 | C27: May/June | D27: 9708/22 | E27: A | F27: 1 | G27: b | I27: 2 | J27: 0 | K27: Compare | P27: 6.3 | Q27: Current account of the balance of payments | R27: ;6.3; | S27: 6.3.2 | T27: current account balance, data comparison | U27: Myanmar/Cambodia – EU tariffs on rice | V27: Compare the current account balance of Myanmar with that of Cambodia in 2018. | W27: Both are in deficit (1 mark) The deficit is a greater / more significant % of national income in Cambodia than in Myanmar (1 mark) Guidance: If the candidate states that the deficit is higher in Cambodia then this must not be credited. Do not allow a reference to the current account being negative/better/worse. For the second mark, the candidate must refer to % of national income as specified in the data i.e. Table 1.2 | X27: 6 | Y27: 3 | Z27: question paper
A28: 9708_s21_22_Q1c | B28: 2021 | C28: May/June | D28: 9708/22 | E28: A | F28: 1 | G28: c | I28: 4 | J28: 0 | K28: Explain | P28: 5.4 | Q28: Supply-side policy | R28: ;5.4;6.1; | S28: 5.4.3, 6.1.4 | T28: international competitiveness, supply-side policy, devaluation | U28: Myanmar/Cambodia – EU tariffs on rice | V28: Explain any two policies that could improve the competitiveness of rice from Myanmar and Cambodia in the EU market. | W28: For the identification of a valid policy (1 mark) and for explanation of how the policy could improve the competitiveness of rice (1 mark) e.g. government subsidies to rice producers (1 mark) should lead to lower prices for rice and therefore make rice more price competitive (1 mark) Government incentives for rice producers to carry out R and D (1 mark) may improve the quality of rice and its competitiveness (1 mark) Two policies required (2 × 2 marks) Guidance: A number of policies are acceptable. These include government subsidisation mentioned in the text: • export subsidies • devaluation of the currency to reduce export prices etc. Do not reward references to depreciation unless it is made clear that this is a ‘managed’ depreciation. Policies can also be designed to improve quality, productivity, etc. The policies must relate to government action and not action by individual firms (note – the gov action could be from either Myanmar/Cambodia OR from the EU.) | X28: 7 | Y28: 3 | Z28: question paper
A29: 9708_s21_22_Q1d | B29: 2021 | C29: May/June | D29: 9708/22 | E29: A | F29: 1 | G29: d | I29: 6 | J29: 0 | K29: Discuss | O29: to what extent | P29: 6.2 | Q29: Protectionism | R29: ;6.2;2.2; | S29: 6.2.2, 2.2.7 | T29: tariffs, PED, XED, alternative markets | U29: Myanmar/Cambodia – EU tariffs on rice | V29: Discuss two factors that will determine the extent of the impact the EU tariffs will have on the economies of Myanmar and Cambodia. | W29: For each relevant factor identified (1 mark) explained (1 mark) and developed to show the impact on the economies of Myanmar and Cambodia (1 mark) e.g. The ped of rice (from Myanmar and Cambodia in the EU) (1 mark). If the demand is price inelastic this means that the rise in price will lead to a less than proportionate fall in QD (1 mark). Therefore, the exports of Myanmar and Cambodia may not significantly reduce (1 mark) Two factors required (2 × 3 marks) Guidance: General factors are required that apply to both countries. These include the price elasticity of demand for rice from these countries in the EU, the cross elasticity of demand between rice from Myanmar and Cambodia and rice from the EU, the extent to which they can find other markets, how the governments of these countries respond e.g. by providing subsidies/devaluing their currencies etc. The impact on the economy may be on balance of payments, employment, growth etc and needs to be clear. Reference to the fact that the tariffs will be substantial as quoted in the text, should be credited. | X29: 8 | Y29: 3 | Z29: question paper
A30: 9708_s21_22_Q1e | B30: 2021 | C30: May/June | D30: 9708/22 | E30: A | F30: 1 | G30: e | I30: 6 | J30: 2 | K30: Discuss | P30: 6.2 | Q30: Protectionism | R30: ;6.2;6.1; | S30: 6.2.3, 6.1.2 | T30: free trade, tariffs, EU, domestic producers | U30: Myanmar/Cambodia – EU tariffs on rice | V30: Discuss the view that the EU should give tariff-free access to the EU market to all producers of rice. | W30: For analysis of the reason(s) why free trade is justified (up to 2 marks) For analysis of the reason(s) why the market should be protected (up to 2 marks) For evaluation that considers both sides of the argument and which is clearly related to the EU market for rice (up to 2 marks) Guidance: This is effectively a question on free trade or protection. Good answers will need to recognise the context of the case study. For example, if they suggest that the European rice farmers are an example of an inefficient ‘sunset industry’ they need to question whether these should be protected. If the market discussed is clearly a market other than rice then do not reward. | X30: 8 | Y30: 3 | Z30: question paper
A31: 9708_s21_22_Q2a | B31: 2021 | C31: May/June | D31: 9708/22 | E31: B | F31: 2 | G31: a | H31: One of 2, 3 or 4 | I31: 8 | J31: 0 | K31: Explain | L31: State | M31: Yes | O31: diagram required | P31: 3.2 | Q31: Methods and effects of government intervention in markets | R31: ;3.2;1.6;3.1; | S31: 3.2.1, 1.6.4, 3.1.2 | T31: demerit good, indirect tax, resource allocation, sugar tax | V31: In 2018 the UK government, concerned about the rise in obesity, particularly amongst young people, imposed a tax on producers of sugar-sweetened drinks. State what is meant by a demerit good, and with the help of a diagram(s) explain how a tax on producers can improve the allocation of resources in the market for sugar-sweetened drinks. | W31: For knowledge and understanding of a demerit good which explains that the term refers to a good that has the cost of consumption underestimated/worse for the consumer than they realise/because of information failure (1 mark) and is overconsumed (1 mark) Application that uses a correctly labelled diagram to explain the impact of an indirect tax on price and quantity. Diagram showing a left shift in the S curve (1 mark) the fall in quantity consumed (1 mark) and the increase in price (1 mark) (up to 3 marks) An explanation that the tax is increasing the cost of production for producers (1 mark), which increases the price and reduces the consumption (1 mark) which removes the market failure/problem of information failure/improves the allocation of resources (1 mark) (up to 3 marks) Guidance: The answer provided must show knowledge and understanding that a demerit good is one that is worse for the consumer than they realise because of information failure. The diagram(s) should show that demerit goods are under-priced and over consumed and also how a tax can improve allocation. | X31: 9 | Y31: 4 | Z31: question paper
A32: 9708_s21_22_Q2b | B32: 2021 | C32: May/June | D32: 9708/22 | E32: B | F32: 2 | G32: b | H32: One of 2, 3 or 4 | I32: 12 | J32: 4 | K32: Compare | L32: Consider | P32: 3.2 | Q32: Methods and effects of government intervention in markets | R32: ;3.2;1.6; | S32: 3.2.4, 3.2.1, 3.2.6, 1.6.4 | T32: minimum price, demerit goods, public health, alternative policies | V32: Compare the likely effectiveness of a policy of imposing minimum prices on demerit goods with one other policy to improve public health and consider which policy is more likely to be successful. | W32: For analysis that explains the likely effectiveness of a minimum price on a demerit good. Maximum of 3 marks if only benefits or drawbacks are considered (up to 4 marks) For analysis that explains the likely effectiveness of one other policy. Maximum of 3 marks if only benefits or drawbacks are considered (up to 4 marks) And for evaluation that clearly compares the effectiveness of both policies (3 marks) that leads to a reasoned conclusion as to which policy is more likely to be successful (1 mark) Guidance: The effectiveness of a minimum price is dependent upon the ability to control prices and the likelihood that unauthorised / illegal / underground / informal / hidden markets might arise. Other policies include indirect taxes, education campaigns, subsidisation of alternatives. No credit for simply referring to part (a) | X32: 10 | Y32: 4 | Z32: question paper
A33: 9708_s21_22_Q3a | B33: 2021 | C33: May/June | D33: 9708/22 | E33: B | F33: 3 | G33: a | H33: One of 2, 3 or 4 | I33: 8 | J33: 0 | K33: Explain | P33: 2.2 | Q33: PED, YED and XED | R33: ;2.2; | S33: 2.2.1, 2.2.3 | T33: XED, substitutes, complements, unrelated goods | V33: Explain how the concept of cross-elasticity of demand can be used to distinguish between goods that are substitutes, those that are complements and those that have no relationship. | W33: For knowledge and understanding of the concept of cross elasticity of demand. What it measures (1 mark) and the formula (1 mark) And application explaining that a positive value indicates a substitute (1 mark) and explains why (1 mark) And explains that a negative value indicates a complement (1 mark) and why (1 mark) And explains that a value of zero indicates unrelated goods (1 mark) and why (1 mark) Guidance: For knowledge and understanding, the candidate must display an awareness of the idea of ‘responsiveness’ as well as an accurate formula | X33: 10 | Y33: 4 | Z33: question paper
A34: 9708_s21_22_Q3b | B34: 2021 | C34: May/June | D34: 9708/22 | E34: B | F34: 3 | G34: b | H34: One of 2, 3 or 4 | I34: 12 | J34: 4 | K34: Discuss | L34: Consider | O34: to what extent | P34: 2.2 | Q34: PED, YED and XED | R34: ;2.2; | S34: 2.2.8 | T34: YED, PED, recession, business decisions | V34: An economy is experiencing a fall in average incomes during a severe recession. Discuss the extent to which the concepts of income elasticity of demand and price elasticity of demand might be useful to an entrepreneur in this economy and consider which would be more useful. | W34: For analysis that explains the usefulness of income elasticity of demand to an entrepreneur when incomes are falling. (Up to 4 marks) For analysis that explains the usefulness of price elasticity of demand to an entrepreneur when incomes are falling (Up to 4 marks) And for evaluation that clearly compares the usefulness of each concept (3 marks) that leads to a reasoned conclusion as to which is the most useful (1 mark) Guidance: Income elasticity of demand would be useful to an entrepreneur because it would indicate those goods that are likely to experience a decrease in demand and those that should experience a rise in demand i.e. normal goods and inferior goods respectively Price elasticity of demand will inform an entrepreneur of the possibility of changing prices to increase revenue. The estimates might be used by an entrepreneur or firms for sales forecasting, investment decisions, production planning, location and new markets. There are no KU marks awarded in part (b) for merely explaining/ defining terms or phrases within the question | X34: 11 | Y34: 4 | Z34: question paper
A35: 9708_s21_22_Q4a | B35: 2021 | C35: May/June | D35: 9708/22 | E35: B | F35: 4 | G35: a | H35: One of 2, 3 or 4 | I35: 8 | J35: 0 | K35: Explain | M35: Yes | O35: diagram required | P35: 4.6 | Q35: Price stability | R35: ;4.6;4.3; | S35: 4.6.1, 4.3.12 | T35: deflation, AD/AS, causes of deflation | V35: Explain what is meant by deflation and use aggregate demand and aggregate supply diagrams to explain how it might arise in an economy. | W35: For knowledge and understanding of the meaning of deflation. Deflation is a sustained fall (1 mark) in the general price level (1 mark) One mark maximum for stating it is the opposite of inflation/negative inflation ( up to 2 marks max for KU) And application that uses an appropriate and accurate diagram to show how deflation might be caused by a fall in aggregate demand. For an explanation why AD may fall (1 mark) a diagram that shows the resulting change in general price level (1 mark) and explains how this causes deflation (1 mark) (up to 3 marks) And application that uses an appropriate and accurate diagram to show how deflation might be caused by a rise in aggregate supply. For an explanation as to why AS may increase (1 mark) a diagram that shows the resulting change in general price level (1 mark) and explains how this causes deflation (1 mark) (up to 3 marks) Guidance: Do not reward ‘micro’ diagrams showing S/D, P/Q Reasons why AD may fall include: fall in either C, I, G, X or rise in M. Reasons why AS may rise include: increased investment, falling costs | X35: 12 | Y35: 4 | Z35: question paper | AD35: 9708_s24_22_Q1b (58%)
A36: 9708_s21_22_Q4b | B36: 2021 | C36: May/June | D36: 9708/22 | E36: B | F36: 4 | G36: b | H36: One of 2, 3 or 4 | I36: 12 | J36: 4 | K36: Discuss | O36: compare two options | P36: 5.3 | Q36: Monetary policy | R36: ;5.3;5.2;4.6; | S36: 5.3.3, 5.2.6, 4.6.1 | T36: monetary policy, fiscal policy, deflation | V36: Discuss whether a government should use monetary policy or fiscal policy to solve the problem of deflation in an economy. | W36: For analysis that explains how monetary policy can be used to stimulate aggregate demand with due reference to the strengths and weaknesses of this approach. Maximum 3 marks if only strengths or weaknesses are explained (up to 4 marks) For analysis that explains how fiscal policy can be used to stimulate aggregate demand with due reference to the strengths and weaknesses of this approach. Maximum 3 marks if only strengths or weaknesses are explained (up to 4 marks) And for evaluation that clearly compares the use of each policy to solve the problem of deflation (3 marks) that leads to a reasoned conclusion as to which policy may be the most appropriate (1 mark) Guidance: Monetary policy can include exchange rate policy and should be rewarded. The evaluation here should compare the strengths and weaknesses of each approach and arrive at a conclusion based upon this assessment. If a candidate gets MP and FP the wrong way around throughout their response then award a max of [1 + 1] marks for an understanding of both economic policy instruments. A response such as this should be recorded as [1 + 1 + 0] in the text box. There are no KU marks awarded in part (b) for merely explaining / defining terms or phrases within the question | X36: 13 | Y36: 4 | Z36: question paper | AD36: 9708_s22_23_Q3b (61%)
A37: 9708_s21_23_Q1ai | B37: 2021 | C37: May/June | D37: 9708/23 | E37: A | F37: 1 | G37: a(i) | I37: 2 | J37: 0 | K37: Describe | P37: 2.1 | Q37: Demand and supply curves | R37: ;2.1; | S37: 2.1.2 | T37: data trend, bus journeys | U37: Great Britain/Luxembourg – transport and free public transport | V37: Use the information in Fig. 1.1 to describe the changes in the number of journeys by bus in Great Britain from 1997/98 to 2017/18. | W37: Various possibilities including: • Bus passenger journeys outside London have fallen over the period/from c 3.2 bn to c 2.7bn • Bus passenger journeys in London increased up to 2013/14 but have then fallen slightly/overall have increased/from c 1.3 bn to c2.3 bn • Overall bus passenger journeys have increased (1 mark for any of these) Guidance: The data clearly shows that overall during the period bus passenger journeys outside of London have fallen BUT within London, over the same period bus passenger journeys have increased. Within London, passenger journeys increased up to 2013/14 but declined thereafter. | X37: 6 | Y37: 3 | Z37: question paper | AA37: Chart needed: Fig. 1.1 is a line chart with no printed values, so the source extract here cannot show it. Use the original paper.
A38: 9708_s21_23_Q1aii | B38: 2021 | C38: May/June | D38: 9708/23 | E38: A | F38: 1 | G38: a(ii) | I38: 2 | J38: 0 | K38: Explain | P38: 2.1 | Q38: Demand and supply curves | R38: ;2.1;4.6; | S38: 2.1.3, 4.6.2 | T38: price changes, determinants of demand, index numbers | U38: Great Britain/Luxembourg – transport and free public transport | V38: Using the information in Fig. 1.2, explain one of the changes you have identified. | W38: Various possibilities including: • Public transport fares have increased above the rate of inflation • Bus passenger fares have increased faster than rail fares for most of the period • Bus fares have increased at their largest rate of growth since 2016 • Substituting bus journeys for rail journeys Identify the factor (1 mark) and explain with reference to the selected change in 1(a)(i) (1 mark) OFR applied if candidate wrongly identifies changes for part a but then provides a valid explanation 1 +1 Guidance: Explanations are likely to focus on price elasticity of demand/consumer preferences and/or cross elasticity of demand/degree of substitutability between bus journeys and other forms of transport. | X38: 6 | Y38: 3 | Z38: question paper | AA38: Chart needed: Fig. 1.2 is a line chart with no printed values, so the source extract here cannot show it. Use the original paper.
A39: 9708_s21_23_Q1b | B39: 2021 | C39: May/June | D39: 9708/23 | E39: A | F39: 1 | G39: b | I39: 2 | J39: 0 | K39: Explain | P39: 1.1 | Q39: Scarcity, choice and opportunity cost | R39: ;1.1;3.2; | S39: 1.1.3, 3.2.2 | T39: opportunity cost, subsidy | U39: Great Britain/Luxembourg – transport and free public transport | V39: Explain how opportunity cost can be applied to the Great British government’s decision to subsidise public transport. | W39: A simple understanding of what opportunity cost is (1 mark) Which is applied to a valid example in context (1 mark) Guidance: Valid examples could include money committed to subsidising public transport may have been used for new roads, education, health services etc. | X39: 7 | Y39: 3 | Z39: question paper
A40: 9708_s21_23_Q1c | B40: 2021 | C40: May/June | D40: 9708/23 | E40: A | F40: 1 | G40: c | I40: 2 | J40: 0 | K40: Explain | P40: 1.6 | Q40: Classification of goods and services | R40: ;1.6; | S40: 1.6.1 | T40: free goods, zero price, opportunity cost | U40: Great Britain/Luxembourg – transport and free public transport | V40: Explain whether public transport in Luxembourg has become a free good as a result of all prices being removed. | W40: Explain what is meant by a free good (1 mark) Explain why this is not a free good (1 mark) Guidance: Explanation must refer to factors of production being needed to provide transport services i.e. there is a cost involved which is not the case with free goods Do not reward answers that clearly confuse free goods with public goods | X40: 7 | Y40: 3 | Z40: question paper
A41: 9708_s21_23_Q1d | B41: 2021 | C41: May/June | D41: 9708/23 | E41: A | F41: 1 | G41: d | I41: 6 | J41: 1 | K41: Discuss | P41: 3.2 | Q41: Methods and effects of government intervention in markets | R41: ;3.2;2.2; | S41: 3.2.4, 2.2.6 | T41: minimum price, congestion, PED for fuel | U41: Great Britain/Luxembourg – transport and free public transport | V41: Discuss whether a minimum price for fuel would be effective in reducing the congestion caused by the demand for roads exceeding supply. | W41: For an analysis of the effect of introducing a minimum price in a market. (up to 3 marks) For analysis which explains why a minimum price may not be effective. (up to 3 marks) MAXIMUM of 5 marks for analysis 1 mark for a justified conclusion as to whether a minimum price would be effective in reducing congestion Guidance: A minimum price for fuel above the equilibrium price would increase the price for car users and in theory, lead to reduced demand and reduced congestion. However, this would only be effective if the demand for fuel was price elastic. In addition, it will lead to excess supply and the possible formation of informal markets. It also depends on the ability of the government to maintain and enforce the minimum price. | X41: 7 | Y41: 3 | Z41: question paper
A42: 9708_s21_23_Q1e | B42: 2021 | C42: May/June | D42: 9708/23 | E42: A | F42: 1 | G42: e | I42: 6 | J42: 1 | K42: Discuss | O42: compare two options | P42: 3.2 | Q42: Methods and effects of government intervention in markets | R42: ;3.2;1.4;2.4; | S42: 3.2.3, 2.4.4 | T42: free provision, resource allocation, public transport | U42: Great Britain/Luxembourg – transport and free public transport | V42: Discuss whether making public transport free to consumers is the best way to allocate resources in public transport markets. | W42: Analysis of the benefits of free public transport (up to 3 marks) Analysis of the benefits of any other valid policy (up to 3 marks) MAXIMUM of 5 marks for analysis Award up to 1 mark for an evaluation of which policy is likely to be the most effective Guidance: Various alternative policies could be – Maximum prices for bus and rail fares – Transfer payments for bus and rail transport users – Subsidies | X42: 8 | Y42: 3 | Z42: question paper
A43: 9708_s21_23_Q2a | B43: 2021 | C43: May/June | D43: 9708/23 | E43: B | F43: 2 | G43: a | H43: One of 2, 3 or 4 | I43: 8 | J43: 0 | K43: Explain | P43: 2.2 | Q43: PED, YED and XED | R43: ;2.2; | S43: 2.2.1, 2.2.3 | T43: XED, complements, substitutes, tourism | V43: Market research has estimated that the cross-elasticity of demand for hotels in Barbados with respect to the price of flights to Barbados is –2.5, and that the cross-elasticity of demand for flights to Antigua with respect to the price of flights to Barbados is +0.5. Explain what is meant by cross-elasticity of demand and what these values mean in terms of the effect of changes in the price of flights to Barbados on (i) the demand for hotels in Barbados, and (ii) the demand for flights to Antigua. | W43: For knowledge and understanding of the concept of cross elasticity of demand. What it measures (1 mark) and the formula (1 mark) (i) Identify that this would suggest hotels are a complement to flights due to the negative sign (1 mark) explain why the value is negative (1 mark) with reference to the size of the coefficient (1 mark) (up to 3 marks) (ii) Identify that this would suggest that flights to Antigua are a substitute for flights to Barbados due to the positive sign (1 mark) explain why the value is positive (1 mark) with reference to the size of the coefficient (1 mark) (up to 3 marks) Guidance: An increase in the price of flights to Barbados will lead to a larger percentage fall in demand for hotel accommodation (complements) and a smaller percentage increase in demand for flights to Antigua (substitutes). In the explanations, reference must be made to the significance of the size of the coefficient for the third mark | X43: 9 | Y43: 3 | Z43: question paper
A44: 9708_s21_23_Q2b | B44: 2021 | C44: May/June | D44: 9708/23 | E44: B | F44: 2 | G44: b | H44: One of 2, 3 or 4 | I44: 12 | J44: 4 | K44: Discuss | P44: 3.2 | Q44: Methods and effects of government intervention in markets | R44: ;3.2;2.2; | S44: 3.2.1, 2.2.7 | T44: indirect tax, tax revenue, PED, tourism | V44: Growing pressures on the budget and on the environment from increasing tourist numbers to Barbados led the government to announce a new indirect tax on incoming tourists in June 2018. Discuss the likely effectiveness of the new indirect tax in raising tax revenue and reducing tourist numbers. | W44: For an analysis of how the new tax will raise tax revenue and reduce tourist numbers (up to 4 marks) For an analysis of other factors which may reduce the effectiveness of the new indirect tax (up to 4 marks) Up to 4 marks for an evaluation of the likely impact on the market of the new indirect tax, that may also consider other ways in which the government could raise additional revenue and reduce tourist numbers. Reserve 1 mark for a reasoned conclusion as to whether the new indirect tax would be truly effective Guidance: The effectiveness of the tax will depend on the PED for holidays in Barbados; incidence will vary with rate of tax. A diagram would help here although it is not essential. There are no KU marks awarded in part b for merely explaining/defining terms or phrases within the question | X44: 10 | Y44: 3 | Z44: question paper
A45: 9708_s21_23_Q3a | B45: 2021 | C45: May/June | D45: 9708/23 | E45: B | F45: 3 | G45: a | H45: One of 2, 3 or 4 | I45: 8 | J45: 0 | K45: Explain | P45: 4.3 | Q45: AD and AS analysis | R45: ;4.3; | S45: 4.3.6, 4.3.7, 4.3.9 | T45: aggregate supply, SRAS, LRAS, AS shift | V45: Explain what is meant by aggregate supply and explain one reason why the aggregate supply curve of an economy would shift outwards in (i) the short run, and (ii) the long run. | W45: For explanation of aggregate supply e.g. total output in an economy (1 mark) that distinguishes between short run and long run (1 mark) (up to 2 marks) Identify a reason (1 mark) plus up to 2 marks for an explanation of why this causes the SRAS to move outwards. (up to 3 marks) Identify a reason (1 mark) plus up to 2 marks for an explanation of why this causes the LRAS to move (up to 3 marks) Guidance: A shift outwards of the AS curve can be due to – an increase in the supply of labour – net investment – other factor inputs – devaluation of the exchange rate – government regulations – discovery of new resources – better education and training – advances in technology | X45: 11 | Y45: 3 | Z45: question paper
A46: 9708_s21_23_Q3b | B46: 2021 | C46: May/June | D46: 9708/23 | E46: B | F46: 3 | G46: b | H46: One of 2, 3 or 4 | I46: 12 | J46: 4 | K46: Discuss | P46: 4.3 | Q46: AD and AS analysis | R46: ;4.3;4.4;4.6; | S46: 4.3.12, 4.4.5, 4.6.4 | T46: aggregate demand increase, growth, inflation, employment | V46: Discuss whether an increase in aggregate demand would be of overall benefit for an economy. | W46: For an analysis of the benefits of an increase in aggregate demand to the economy (up to 4 marks) For an analysis of the possible problems for an economy if aggregate demand increases (up to 4 marks) Up to 4 marks for an evaluation which clearly compares the benefits and the problems for an economy resulting from an increase in AD with one mark reserved for a reasoned conclusion Guidance: A good answer should consider firms, government and consumers/workers The benefits for an increase in AD may include economic growth, higher employment etc The problems may include inflation, current account deficit etc There are no KU marks awarded in part b for merely explaining/defining terms or phrases within the question | X46: 11 | Y46: 3 | Z46: question paper
A47: 9708_s21_23_Q4a | B47: 2021 | C47: May/June | D47: 9708/23 | E47: B | F47: 4 | G47: a | H47: One of 2, 3 or 4 | I47: 8 | J47: 0 | K47: Explain | P47: 6.2 | Q47: Protectionism | R47: ;6.2;6.1; | S47: 6.2.1, 6.1.2 | T47: free trade area, customs union, trade agreements | V47: Explain how a free trade area differs from a customs union and explain two reasons why countries move towards tariff-free trade. | W47: Up to 2 marks for an explanation of the difference between a free trade area and a customs union. Knowledge and understanding of what is meant by a free trade area (1 mark) and knowledge and understanding of how this differs from a customs union (1 mark) Identify a reason why countries may move to tariff free trade (1 mark) and up to 2 marks that clearly explains the benefits to countries × 2 (3 marks maximum per reason) Guidance: The description of the principle of comparative advantage is not required. The main difference is in terms of a common external tariff in a customs union. Reference to common policies as in the case of the EU is also OK. Various benefits of free trade include – specialisation – higher living standards – cheaper and better quality products and more choice – increased employment – to benefit from the principle of comparative advantage | X47: 12 | Y47: 4 | Z47: question paper
A48: 9708_s21_23_Q4b | B48: 2021 | C48: May/June | D48: 9708/23 | E48: B | F48: 4 | G48: b | H48: One of 2, 3 or 4 | I48: 12 | J48: 4 | K48: Discuss | P48: 6.1 | Q48: The reasons for international trade | R48: ;6.1;6.2; | S48: 6.1.2, 6.2.3 | T48: free trade, net importers, net exporters | V48: Discuss the view that the gains from tariff-free trade are greater for countries who are net importers than for countries who are net exporters. | W48: Up to 4 marks for an analysis of the benefits/gains /advantages and disadvantages from tariff-free trade for countries who are net importers. Maximum of 3 marks for answers that only considers either advantages or disadvantages Up to 4 marks for an analysis of the benefits/gains /advantages and disadvantages from tariff free trade for countries who are net exporters. Maximum of 3 marks for answers that only considers either advantages or disadvantages Up to 4 marks for an evaluation that clearly compares the impact of tariff free trade on both countries who are net importers and those who are net exporters with 1 mark reserved for a valid conclusion as to whether the statement may be justified. Guidance: This is an unusual statement, given that economic theory tends to concentrate on the benefits of increased exports not imports. The benefits from tariff-free imports can include cheaper supplies, better quality and range of goods, puts pressure on domestic producers to be more efficient etc. But the disadvantages may include a threat to domestic businesses. The benefits for net exporters include higher growth, increased employment etc. but the disadvantages may include higher inflation. There are no KU marks awarded in part b for merely explaining/defining terms or phrases within the question | X48: 13 | Y48: 4 | Z48: question paper
A49: 9708_w21_21_Q1a | B49: 2021 | C49: Oct/Nov | D49: 9708/21 | E49: A | F49: 1 | G49: a | I49: 2 | J49: 0 | K49: Explain | P49: 4.6 | Q49: Price stability | R49: ;4.6; | S49: 4.6.3, 4.6.5 | T49: real value of money, inflation | U49: Zimbabwe/Venezuela – hyperinflation | V49: Explain how inflation can halve the ‘real value’ of money. | W49: • The real value is the quantity of products that can be bought for a certain amount of money (1 mark) • If prices double, the quantity that can be bought will be halved (1 mark) | X49: 5 | Y49: 3 | Z49: question paper | AE49: Most candidates were able to correctly explain how inflation could reduce the ‘real value’ of money, by commenting on its reduced purchasing power, but relatively few were able to explain that the ‘real value’ of money would be halved when prices of products doubled.
A50: 9708_w21_21_Q1b | B50: 2021 | C50: Oct/Nov | D50: 9708/21 | E50: A | F50: 1 | G50: b | I50: 4 | J50: 0 | K50: Explain | M50: Yes | O50: diagram required | P50: 4.6 | Q50: Price stability | R50: ;4.6;2.4; | S50: 4.6.4, 2.4.2 | T50: expectations, panic buying, demand shift, shortages | U50: Zimbabwe/Venezuela – hyperinflation | V50: With the aid of a diagram, explain why ‘rapid price rises encourage panic-buying by consumers, creating shortages that further increase inflation’. | W50: For an appropriate diagram that shows a further increase in inflation (up to 2 marks) For an explanation of why rapid price rises encourage panic-buying by consumers, creating shortages that further increase inflation (up to 2 marks) Guidance: Candidates can adopt a micro or a macro approach: • increase in demand • excess demand created in short run • price increases • causes expectation of further price increases • so more purchases • leading to a price spiral | X50: 5 | Y50: 3 | Z50: question paper | AE50: A number of candidates were able to explain why rapid price rises encouraged panic-buying by consumers, going on to explain that this was likely to cause shortages that would have the effect of further increasing inflation. It was expected that candidates would adopt a macro approach to the question, but candidates could adopt either a macro or a micro approach to answering the question, although if a micro approach was adopted, it was expected that candidates would refer to the rise in price of more than one product. Some of the diagrams were of a good standard but some were poorly drawn and/or poorly labelled. This was especially the case with the macro diagrams where the vertical axis was often labelled ‘P’ rather than ‘price level’ and the horizontal axis ‘Q’ rather than ‘real output’.
A51: 9708_w21_21_Q1c | B51: 2021 | C51: Oct/Nov | D51: 9708/21 | E51: A | F51: 1 | G51: c | I51: 2 | J51: 0 | K51: Explain | P51: 4.6 | Q51: Price stability | R51: ;4.6;5.3; | S51: 4.6.5 | T51: functions of money, hyperinflation | U51: Zimbabwe/Venezuela – hyperinflation | V51: With reference to one function of money explain why hyperinflation in Zimbabwe caused the country to abandon its currency in 2008. | W51: For an explanation of the potential impact of hyperinflation on one function of money: • a medium of exchange (up to 2 marks) • a unit of account/a measure of value (up to 2 marks) • a store of value/a store of wealth (up to 2 marks) • a standard for deferred payment (up to 2 marks) 2 marks maximum 1 mark for the identification of one function of money 1 mark for the explanation of how hyperinflation might impact on this function and cause the country to abandon its currency Guidance: Hyperinflation can prevent money serving as a medium of exchange when people lose confidence in money Hyperinflation, as in Zimbabwe, can prevent money serving as a unit of account/a measure of value in an economy Hyperinflation is likely to prevent money serving effectively as a store of value/a store of wealth because its real value, i.e. its purchasing power, will be reduced Hyperinflation is likely to prevent money serving effectively as a standard for deferred payment because people will be reluctant to exchange anything on a credit basis if the value of money is rapidly falling | X51: 5 | Y51: 3 | Z51: question paper | AA51: Functions of money: not in the 2023+ AS syllabus (now A Level). | AE51: Many candidates were able to refer to one function of money, such as a medium of exchange, a unit of account/a measure of value, a store of value/wealth or a standard for deferred payment. However, a number of candidates referred to a characteristic or an attribute of money, rather than a function, such as portability or acceptability. Some of the answers were rather vague in terms of linking the function to hyperinflation, leading to Zimbabwe abandoning its currency in 2008.
A52: 9708_w21_21_Q1d | B52: 2021 | C52: Oct/Nov | D52: 9708/21 | E52: A | F52: 1 | G52: d | I52: 6 | J52: 1 | K52: Discuss | P52: 5.3 | Q52: Monetary policy | R52: ;5.3;4.3;4.6; | S52: 5.3.4, 4.3.12 | T52: monetary policy, investment, inflation, policy conflict | U52: Zimbabwe/Venezuela – hyperinflation | V52: Using aggregate demand and aggregate supply analysis, discuss whether it is possible to use monetary policy to achieve both a high level of investment and a low rate of inflation. | W52: For an explanation of the use of monetary policy to achieve both a high level of investment and a low rate of inflation, using AD/AS analysis (up to 3 marks) For an explanation of the limitations of monetary policy in achieving both a high level of investment and a low rate of inflation, using AD/AS analysis (up to 3 marks) 5 marks maximum Reserve 1 mark for a conclusion 6 marks maximum Guidance: Monetary policy involves the use of changes in interest rates and/or changes in the money supply and/or changes in the exchange rate If an expansionary policy is used to encourage a high level of investment, interest rates could be lowered Such an approach is likely to increase the level of aggregate demand in an economy and this could lead to an increase in inflation if AD exceeds AS However, investment could increase AS in the economy and contribute to a lower rate of inflation The timeframe is important; AD increases will occur before the investment can increase AS and so it is likely that the short- run effect would be inflationary, but the long-run effect may not be It may be possible to lower the interest rate without causing inflation if an economy has spare capacity; if the LRAS curve is horizontal, investment could be encouraged (AD shifting right) without inflation | X52: 6 | Y52: 3 | Z52: question paper | AE52: A number of candidates did make a good attempt to discuss whether it was possible to use monetary policy to achieve both a high level of investment and a low rate of inflation, although many of them focused on one or the other objective, but not both. The better answers pointed out that both objectives could be achieved if an economy had spare capacity and there were some good references to the horizontal LRAS curve. A few candidates made no reference to aggregate demand and aggregate supply analysis in their answers, despite the fact that the question explicitly required candidates to do so. Some candidates wrote very generally about monetary policy without focusing on the two objectives stated in the question. A number of candidates did not offer a conclusion, even though it was a ‘discuss’ question.
A53: 9708_w21_21_Q1e | B53: 2021 | C53: Oct/Nov | D53: 9708/21 | E53: A | F53: 1 | G53: e | I53: 6 | J53: 1 | K53: Discuss | P53: 4.6 | Q53: Price stability | R53: ;4.6;3.3; | S53: 4.6.5 | T53: consequences of hyperinflation, winners and losers, debtors and creditors | U53: Zimbabwe/Venezuela – hyperinflation | V53: Discuss whether everybody in an economy such as Venezuela would be worse off as a result of hyperinflation. | W53: For an explanation that some people in an economy could be worse off as a result of a high rate of inflation (up to 3 marks) For an explanation that some people in an economy could be better off as a result of a high rate of inflation (up to 3 marks) 5 marks maximum Reserve 1 mark for a conclusion 6 marks maximum Guidance: Possible negative consequences of a high rate of inflation/hyperinflation: • it erodes the real value of money • it reduces individuals’ purchasing power • it makes a country’s exports uncompetitive • it creates a redistribution of income, with those on fixed incomes badly affected • menu costs • shoe leather costs • it creates uncertainty in an economy Possible positive consequences of a high rate of inflation/hyperinflation: • if prices rise by more than costs, it can increase firms’ profits • this can encourage firms to expand, leading to a reduction in the level of unemployment in an economy • borrowers will gain from inflation because the debt will be less in real terms | X53: 7 | Y53: 3 | Z53: question paper | AE53: Many candidates made quite a good attempt to discuss whether everybody in an economy would be worse off as a result of hyperinflation, contrasting the potential disadvantages of inflation, such as the reduction of purchasing power and the existence of menu and shoe leather costs, with the potential advantages, such as the benefit to borrowers and the possible increase in firms’ profits. Unfortunately, a number of candidates did not offer a conclusion, even though it was a ‘discuss’ question.
A54: 9708_w21_21_Q2a | B54: 2021 | C54: Oct/Nov | D54: 9708/21 | E54: B | F54: 2 | G54: a | H54: One of 2, 3 or 4 | I54: 8 | J54: 0 | K54: Compare | M54: Yes | O54: diagram required | P54: 1.5 | Q54: Production possibility curves | R54: ;1.5; | S54: 1.5.3, 1.5.4 | T54: PPC, movement vs shift, resources | V54: With the aid of a diagram, compare what happens to an economy’s resources to cause a movement along its production possibility curve with what happens to an economy’s resources to cause a shift of its production possibility curve. | W54: For correct diagram: Axes correctly labelled: Good A and Good B or equivalent (e.g. capital goods and consumer goods or agricultural products and manufactured products) (1 mark) PPC correctly drawn, touching both axes (1 mark) KU: 2 marks maximum Application of PPC in terms of a movement along a curve (up to 3 marks) Application of PPC in terms of a shift of a curve (up to 3 marks) APP: 6 marks maximum Guidance: The shift of the PPC can be to the right or to the left or both A movement along a PPC shows different combinations of outputs that can be produced from the given resources; this movement along a PPC from one point to another will involve a re-allocation of those resources A shift of a PPC, say to the right, comes about as a result of an increase in the quantity and/or quality of resource/s, leading to an expansion in the productive capacity or potential output of an economy, allowing more of one/both goods to be produced | X54: 8 | Y54: 3 | Z54: question paper | AE54: In this part of the question, candidates were required to compare what happens to an economy’s resources to cause a movement along its production possibility curve with what happens to an economy’s resources to cause a shift of its production possibility curve. Most answers demonstrated a sound knowledge and understanding of the differences between the two, with a movement involving opportunity cost and a reallocation of existing resources whereas a shift would involve an expansion in the productive capacity of an economy, actual economic growth and the ability to produce more of both goods. The question required a diagram to be drawn and two errors with the diagrams were noticeable on many scripts. Firstly, the axes were often labelled ‘P’ and ‘Q’ rather than ‘Good A’ and ‘Good B’ or ‘agricultural goods’ and ‘manufactured goods’. Secondly, the production possibility curves often failed to touch the two axes; it is a characteristic of such curves that they must touch the two axes. In a few cases, the reference to a production possibility curve was not understood and candidates drew a demand and supply diagram instead of a PPC.
A55: 9708_w21_21_Q2b | B55: 2021 | C55: Oct/Nov | D55: 9708/21 | E55: B | F55: 2 | G55: b | H55: One of 2, 3 or 4 | I55: 12 | J55: 4 | K55: Discuss | O55: absolute claim (always/only/alone); benefits vs costs | P55: 1.4 | Q55: Resource allocation in different economic systems | R55: ;1.4; | S55: 1.4.1, 1.4.2 | T55: planned economy, market economy, transition | V55: Discuss whether the advantages of a transition from a planned economy to a market economy always outweigh the disadvantages. | W55: For Analysis Analysis of the advantages of a transition from a planned economy to a market economy (up to 4 marks) Analysis of the disadvantages of a transition from a planned economy to a market economy (up to 4 marks) AN: 8 marks maximum For Evaluation For exercising some judgement on whether the advantages of a transition from a planned economy to a market economy always outweigh the disadvantages (up to 4 marks) Reserve 1 mark for a conclusion EV: 4 marks maximum Guidance: Advantages of a transition from a planned economy to a market economy: • existence of price mechanism • prices operate as signals to indicate consumer preferences • private sector ownership/decision- making with no or very little government intervention • competition between firms can lead to greater efficiency Disadvantages of a transition from a planned economy to a market economy: • some products will be under-provided and under-consumed • some products will be over-provided and over-consumed • some products will not be provided or consumed at all • there will be consequences of information failure In addition to the market failures outlined above, there could also be negative consequences of a market economy, including: • a higher level of unemployment • a higher level of inflation | X55: 9 | Y55: 3 | Z55: question paper | AD55: 9708_m22_22_Q2b (75%) | AE55: In the second part of the question, candidates were required to discuss whether the advantages of a transition from a planned economy to a market economy always outweighed the advantages. Most candidates were able to provide quite a reasonable analysis of the various advantages, such as the operation of the price mechanism in signalling consumer preferences and the possibility of competition between firms leading to greater efficiency, and the various disadvantages, such as the under-production of merit goods, the over-production of demerit goods and the non-provision of public goods. There was a very clear ‘steer’ in the question, which focused on whether the advantages would ‘always’ outweigh the disadvantages, strongly indicating that this might not always be the case. A few candidates misread the question and wrote about a transition from a planned economy to a mixed economy rather than to a market economy. Most candidates provided little, if any, evaluation, even though four marks were available for evaluation in addition to the eight marks available for analysis.
A56: 9708_w21_21_Q3a | B56: 2021 | C56: Oct/Nov | D56: 9708/21 | E56: B | F56: 3 | G56: a | H56: One of 2, 3 or 4 | I56: 8 | J56: 0 | K56: Explain | M56: Yes | O56: diagram required | P56: 3.2 | Q56: Methods and effects of government intervention in markets | R56: ;3.2;2.5; | S56: 3.2.4, 2.5.1 | T56: minimum price, excess supply, consumers and producers | V56: With the aid of a diagram, explain the consequences for consumers and producers of introducing a minimum price in the market for a product. | W56: For Knowledge and Understanding For correct diagram: Axes correctly labelled: P/Q (1 mark) Minimum price shown above equilibrium in diagram (demand and supply curves need to be correctly labelled) (1 mark) KU: 2 marks maximum For Application Consequences for consumers of the establishment of a minimum price in a market (up to 3 marks) Consequences for producers of the establishment of a minimum price in a market (up to 3 marks) APP: 6 marks maximum Guidance: Consequences for consumers of introducing an effective minimum price in the market for a product: • consumers will need to pay a higher price compared to the price that would have been charged where demand and supply in a market were in equilibrium • this will discourage the consumption of the product by consumers • this will be beneficial for consumers if the product is a demerit good Consequences for producers of introducing an effective minimum price in the market for a product: • the minimum price will help producers to increase their incomes • there will be an excess supply that consumers do not buy at the higher minimum price • government action may be required to buy up this excess supply or to restrict production | X56: 10 | Y56: 3 | Z56: question paper | AD56: 9708_m23_22_Q3b (57%) | AE56: In this part of the question, candidates were required to explain the consequences for consumers and producers of introducing a minimum price in the market for a product. Most candidates were able to consider some of the consequences for consumers, such as the fact that they would be required to pay a higher price for the product than would otherwise be the case, although many of them pointed out that if this discouraged the consumption of the product by consumers, this would be beneficial to them if the product was a demerit good. Most candidates were also able to consider some of the consequences for producers, such as the fact that it would be likely to create a situation of excess supply. A number of candidates made some useful references to the impact on consumer surplus and producer surplus. The question required a diagram to be drawn and although most of these showed the position of the minimum price above the equilibrium position, a few of them incorrectly showed the price below the equilibrium position.
A57: 9708_w21_21_Q3b | B57: 2021 | C57: Oct/Nov | D57: 9708/21 | E57: B | F57: 3 | G57: b | H57: One of 2, 3 or 4 | I57: 12 | J57: 4 | K57: Discuss | O57: compare two options | P57: 2.2 | Q57: PED, YED and XED | R57: ;2.2;2.3; | S57: 2.2.8, 2.3.5 | T57: PED, PES, business decisions | V57: Discuss whether decisions made by a business are more likely to be influenced by knowledge of the price elasticity of demand for its product or by knowledge of the price elasticity of supply of its product. | W57: Analysis of the usefulness of knowledge of price elasticity of demand to a business (up to 4 marks) Analysis of the usefulness of knowledge of price elasticity of supply to a business (up to 4 marks) AN: 8 marks maximum For exercising some judgement on whether decisions made by a business are more likely to be influenced by knowledge of the price elasticity of demand for its product or by knowledge of the price elasticity of supply of its product (up to 4 marks) Reserve 1 mark for a conclusion EV: 4 marks maximum Guidance: Potential usefulness of PED: • it can be helpful in giving a business an indication of the extent to which a change in price may affect revenue • this will show that to increase revenue, the price of an elastic good should be reduced and the price of an inelastic good should be increased • however, to be able to make appropriate calculations, a businessman will need to take into account the availability of substitutes, the width of the definition of the product, the amount spent on the product and the time period under consideration Potential usefulness of PES: • it can be helpful in giving a business an indication of the extent to which a change in the price of a product can lead to a change in the quantity supplied of a product • it can help a business to make decisions about how much stock to hold • it can help a business decide on the extent of spare capacity to provide for • it can help a business decide on the factors of production it is going to need Note: No marks for KU of PED and PES | X57: 11 | Y57: 3 | Z57: question paper | AD57: 9708_m24_22_Q3b (57%), 9708_w25_21_Q2b (55%), 9708_w25_22_Q2b (58%) | AE57: In the second part of the question, candidates were required to discuss whether decisions made by a business were more likely to be influenced by knowledge of the price elasticity of demand for its product or by knowledge of the price elasticity of supply of its product. There were a number of good answers which did attempt to analyse the impact of both elasticities on a business. In terms of PED, there was some useful analysis of how price changes could affect the revenue of a firm. In terms of PES, there was some useful analysis of how a firm would need to act in terms of its spare capacity and in relation to the amount of stock to hold. Unfortunately, a number of candidates focused on describing the two types of elasticity and yet there were no knowledge and understanding marks available. There were eight marks available for analysis and four marks for evaluation, but the quality of the evaluation was unfortunately rather limited, with candidates writing very little on which was likely to have the greater influence on a business.
A58: 9708_w21_21_Q4a | B58: 2021 | C58: Oct/Nov | D58: 9708/21 | E58: B | F58: 4 | G58: a | H58: One of 2, 3 or 4 | I58: 8 | J58: 0 | K58: Explain | M58: Yes | O58: diagram required | P58: 6.4 | Q58: Exchange rates | R58: ;6.4;6.3; | S58: 6.4.1, 6.3.3 | T58: fixed exchange rate, central bank intervention, foreign currency reserves, current account deficit | V58: With the aid of a diagram, explain how a central bank intervenes to maintain a fixed exchange rate when the economy is experiencing a current account deficit on its balance of payments. | W58: For correct diagram: Axes correctly labelled: Exchange rate or price of one currency in terms of another/Q of currency (1 mark) Demand and supply curves correctly labelled (1 mark) KU: 2 marks maximum Explanation that a CA deficit causes downward pressure on the exchange rate (up to 3 marks) Explanation of the intervention of a central bank to maintain the exchange rate (up to 3 marks) APP: 6 marks maximum Guidance: CA deficit means that demand for imports exceeds foreign demand for exports, so domestic demand for foreign currency exceeds foreign demand for the domestic currency. This will put downward pressure on the exchange rate If the value of a currency is about to fall, a central bank will increase demand by: • buying the domestic currency, using their foreign currency reserves • and/or increasing interest rates | X58: 12 | Y58: 3 | Z58: question paper | AE58: In this part of the question, candidates were required to explain, with the aid of a diagram, how a central bank might intervene to maintain a fixed exchange rate when a country was experiencing a current account deficit on its balance of payments. There were some reasonable answers in terms of what a central bank might do in such a situation, such as in relation to buying the currency by using foreign currency reserves and/or increasing interest rates. However, relatively few candidates made it clear that such a current account deficit would cause downward pressure on the exchange rate. In terms of the diagram, a common error was the incorrect labelling of the vertical axis as ‘P’; if the diagram is showing the value of one currency in terms of another, this needs to be made clear by labelling the vertical axis as the value of one currency in relation to the value of another or by simply labelling it ‘exchange rate’.
A59: 9708_w21_21_Q4b | B59: 2021 | C59: Oct/Nov | D59: 9708/21 | E59: B | F59: 4 | G59: b | H59: One of 2, 3 or 4 | I59: 12 | J59: 4 | K59: Discuss | P59: 6.5 | Q59: Policies to correct current account imbalances | R59: ;6.5; | S59: 6.5.1, 6.5.2 | T59: expenditure-reducing policy, current account deficit, floating exchange rate | V59: Discuss whether expenditure-reducing policies are likely to reduce the current account deficit on the balance of payments for an economy with a floating exchange rate. | W59: Analysis of the limitations of expenditure-reducing policies in reducing the current account on the balance of payments for an economy with a floating exchange rate (up to 4 marks) AN: 8 marks maximum For exercising some judgement on whether expenditure-reducing policies are likely to reduce the current account deficit on the balance of payments for an economy with a floating exchange rate (up to 4 marks) Reserve 1 mark for a conclusion EV: 4 marks maximum Guidance: Expenditure-reducing policies are actions taken by a government to reduce the total level of spending in an economy They are designed to lead to: • a fall in imports • and/or a rise in exports Examples can include: • raising interest rates • reducing money supply • increasing taxes • reducing public spending Possible limitations can include: • there may still be a strong demand for imports • resources may not be released for exports | X59: 13 | Y59: 3 | Z59: question paper | AD59: 9708_w22_21_Q4b (68%), 9708_m23_22_Q5b (62%), 9708_m24_22_Q4b (62%), 9708_w25_23_Q5b (59%) | AE59: In the second part of the question, candidates were required to discuss whether expenditure- reducing policies were likely to reduce the current account deficit on the balance of payments for an economy with a floating exchange rate. There were a number of reasonable answers on expenditure-reducing policies, but these did not always focus on the reduction of the deficit and when they did, there was often no link provided with the existence of a floating exchange rate. Unfortunately, some candidates wrote about expenditure-switching, rather than expenditure- reducing, policies. Only a minority of candidates offered a sound evaluation in terms of exercising some judgement on whether expenditure-reducing policies were likely to reduce the current account deficit for an economy with a floating exchange rate.
A60: 9708_w21_22_Q1a | B60: 2021 | C60: Oct/Nov | D60: 9708/22 | E60: A | F60: 1 | G60: a | I60: 1 | J60: 0 | K60: Calculate | N60: Yes | O60: uses data | P60: 4.3 | Q60: AD and AS analysis | R60: ;4.3;6.3; | S60: 4.3.2 | T60: imports, aggregate demand, data calculation | U60: India – slowing growth | V60: Calculate import expenditure as a percentage of total demand in India in quarter 1 2019. | W60: 18.5% (1 mark) Guidance: Method of calculation is not required, only the final answer. Accept 18.5 | X60: 6 | Y60: 3 | Z60: question paper | AE60: The data gave percentages for consumption, investment, government, and export expenditure in relation to total demand. Candidates were asked to calculate the percentage of import expenditure. This required knowledge of the formula to calculate total demand and an understanding that the total value must be 100%. Most candidates knew the formula, and many wrote it down, but many failed to apply this knowledge. A common error was to simply add up the figures given which came to 118.5% and give this as the answer rather than recognising that the excess over 100% represented the amount of import expenditure, i.e., 18.5%.
A61: 9708_w21_22_Q1bi | B61: 2021 | C61: Oct/Nov | D61: 9708/22 | E61: A | F61: 1 | G61: b(i) | I61: 2 | J61: 0 | K61: Explain | P61: 2.2 | Q61: PED, YED and XED | R61: ;2.2; | S61: 2.2.1, 2.2.2 | T61: YED, income tax cut | U61: India – slowing growth | V61: The Indian government promised that it would cut income tax to ensure greater purchasing power for consumers. Explain how economists would measure the impact of a cut in income tax upon the demand for different goods such as scooters and smartphones. | W61: For recognition that they would use the income elasticity of demand (1 mark) because this measures the response of demand for a good to a change in income (1 mark) Guidance: For the first mark, all that is required is identification of the measure For the second mark, this must explain what is being measured and/or provide a formula | X61: 6 | Y61: 3 | Z61: question paper | AE61: The first part of a two-part question. This required candidates to recognise that a cut in income tax would increase disposable income and that economists would therefore use YED to calculate the impact on demand for different goods. This knowledge plus some understanding of what YED measures was sufficient for both marks. Whilst many candidates did get full marks, many answered part b instead by focusing on the nature of scooters and smartphones and either failing to refer to the concept of YED or confusing it with PED therefore gaining 0 marks.
A62: 9708_w21_22_Q1bii | B62: 2021 | C62: Oct/Nov | D62: 9708/22 | E62: A | F62: 1 | G62: b(ii) | I62: 2 | J62: 0 | K62: Explain | P62: 2.2 | Q62: PED, YED and XED | R62: ;2.2; | S62: 2.2.3 | T62: YED, normal goods, luxury goods | U62: India – slowing growth | V62: The Indian government promised that it would cut income tax to ensure greater purchasing power for consumers. With reference to the data, explain whether the impact of the income tax cut is likely to be the same on the demand for scooters and the demand for smartphones. | W62: For an explanation that, according to the data, scooters show a decline in demand as incomes are rising, meaning they are inferior goods (1 mark) Whereas smartphones show a rise in demand as incomes are rising, meaning they are normal or luxury goods (1 mark) Guidance: Candidates need to explain that the impact will vary according to the nature of each type of good and apply it to the case of scooters and smartphones. The data suggest that there is ‘continuing growth of incomes’. The data also state that scooter sales are down, yet sales of smartphones have been growing faster than incomes are growing It can be concluded from the data that scooters are inferior goods and smartphones are normal or luxury goods (This would be sufficient for both marks) | X62: 6 | Y62: 3 | Z62: question paper | AE62: Candidates who gained full marks on part (i) often gained both marks for part (ii). However, in complete contradiction of the evidence in the data, some candidates claimed both scooters and smartphones were normal goods therefore failing to answer the question. Those candidates who had effectively answered part (ii) in part (i) often failed to reproduce their answer and made vague attempts to answer this question. This does emphasise the need to read the questions fully before attempting an answer.
A63: 9708_w21_22_Q1c | B63: 2021 | C63: Oct/Nov | D63: 9708/22 | E63: A | F63: 1 | G63: c | I63: 3 | J63: 0 | K63: Identify | L63: Explain | P63: 5.4 | Q63: Supply-side policy | R63: ;5.4; | S63: 5.4.3 | T63: supply-side policy, competitiveness | U63: India – slowing growth | V63: Using the information, identify one policy that could be considered a supply-side measure and explain how this policy could make Indian businesses more competitive. | W63: For an identification of a valid supply-side measure that could make Indian businesses more competitive (1 mark) For an explanation of how this will make businesses more competitive (up to 2 marks) The 3rd mark must refer specifically to ‘more competitive’. For example, one policy is to reduce business taxes (1) which will provide more available money to invest in new technology (1) which will in turn improve quality of goods/services and/or allow prices to be reduced, therefore making the business more competitive (1) Guidance: Supply-side measures mentioned in the extract include cutting income taxes, cutting business taxes and improving infrastructure. However, any valid supply-side measure that might make Indian businesses more competitive is acceptable Any policy chosen as a supply-side measure should be explained as a supply- side tool rather than demand-side to gain any credit at all, even for identification. For example, cutting income taxes should not be credited if it is discussed in terms of a boost to consumption/demand, but only if discussed, for example, as increasing/ improving the labour force | X63: 7 | Y63: 3 | Z63: question paper | AE63: Responses to this question were generally very good and candidates were normally able to identify a valid supply side policy and apply it to explain how this would make Indian businesses more competitive. When approaching a 3-mark question of this type, there is generally 1 mark for identification of the policy, 1 for a brief explanation of how it works, and the 3rd mark is to develop this explanation – in this case to clearly show how Indian businesses would be made more competitive i.e., in terms of price and/or quality. In some cases, the policy was explained by reference to its effect on demand rather than supply and this gained 0 marks. Other problems included a lack of explanation and a simple reference to reducing the price OR a great deal of unnecessary explanation with no clear link to price and/or quality competitiveness. Both these latter problems meant that marks were reduced by at least 1.
A64: 9708_w21_22_Q1d | B64: 2021 | C64: Oct/Nov | D64: 9708/22 | E64: A | F64: 1 | G64: d | I64: 6 | J64: 1 | K64: Discuss | O64: benefits vs costs | P64: 5.3 | Q64: Monetary policy | R64: ;5.3;4.3; | S64: 5.3.3, 5.3.4 | T64: interest rate cut, aggregate demand, inflation risk | U64: India – slowing growth | V64: Discuss whether the advantages of cutting interest rates in the Indian economy would outweigh the disadvantages. | W64: For an identification of the impact of the cut in interest rates upon any component of aggregate demand (1 mark) For an explanation of how this will create possible advantages for India’s economy (up to 2 marks) For an explanation of how this will create possible disadvantages for India’s economy (up to 2 marks) For an evaluative comment on whether the advantages will outweigh the disadvantages (1 mark) Guidance: Cutting interest rates will have a number of effects. There should be an increase in consumption and investment expenditure, and this will increase aggregate demand. In addition, the impact will be an outflow of foreign currency and a fall in the exchange rate. This should stimulate net exports and again aggregate demand will increase. The increase in aggregate demand will stimulate output and employment However, a disadvantage is that demand- pull inflation will occur, and this has internal and external consequences for India’s economy In evaluation, candidates may refer to the possible impact on LRAS due to possible additional investment. This may, of course, obviously offset any inflationary pressure | X64: 8 | Y64: 3 | Z64: question paper | AE64: Again, responses to this question were very pleasing and many candidates gained at least 4 marks out of the possible 6. Most candidates recognised the fact that a reduction in interest rates would lead to an increase in AD or at least one of the components. However, often a great deal of time was wasted in explaining why AD may increase at the expense of analysing the impacts on the Indian economy which was the focus of the question. The advantages discussed were normally an increase in employment and economic growth etc., and the main disadvantages discussed were demand pull inflation and a deficit on the current account due to possible extra spending on imports. The question did however expose a confusion between savings and investment as many candidates suggested that FDI would fall as interest rates fell which of course is not necessarily the case. It does emphasise the need to ensure that candidates fully understand the distinction between savings and investment in economics as this is an extremely common error. A fall in interest rates may lead to a fall in hot money inflows but this is not FDI. The fall in interest rates may also lead to a fall in the exchange rate and this was frequently referred to as a disadvantage without explaining why this may be the case. Clearly it may also be an advantage if it leads to an increase in exports and candidates need to be careful to explain the outcomes and not merely assume a depreciation is a disadvantage. Evaluation was generally quite weak with few candidates moving beyond a simple summary or unexplained conclusion.
A65: 9708_w21_22_Q1e | B65: 2021 | C65: Oct/Nov | D65: 9708/22 | E65: A | F65: 1 | G65: e | I65: 6 | J65: 1 | K65: Consider | O65: compare two options | P65: 1.6 | Q65: Classification of goods and services | R65: ;1.6;3.2;1.4; | S65: 1.6.2, 3.2.3, 1.4.1 | T65: infrastructure, public goods, private vs public provision | U65: India – slowing growth | V65: Consider whether roads and other items of infrastructure in India would be better provided by the private sector or by the government in India. | W65: For an explanation of why some infrastructure either could only or may be better provided by the government (up to 3 marks) For an explanation of why some infrastructure may be better provided by the private sector (up to 3 marks) 5 marks maximum Reserve 1 mark for a reasoned conclusion Guidance: Reasons why some infrastructure may be better provided by the government may include accurate explanation of: • provision of public goods, i.e. those with characteristics of non-rivalry and non- excludability, e.g. street lighting • quasi-public goods, e.g. roads and bridges • free rider problem • merit goods • scale of investment needed Reasons for private sector provision may include: • they are private goods and why, therefore, profit motive applies leading to better efficiency • government budget restrictions • opportunity cost Note: explanations must be accurate, and credit must not be given to answers that simply assert all government funded infrastructure refers to public goods | X65: 9 | Y65: 3 | Z65: question paper | AE65: This question was not answered very well, and the main problem continues to be a lack of understanding of what a public good is. Many candidates either asserted that roads and bridges are public goods or merely grouped all infrastructure as a public good. Whilst it is true that the government funds and provides roads in many countries, they are not true public goods and because of their characteristics of being potentially excludable and rivalrous, they could be provided by the private sector. The distinction between public goods, private goods and merit goods needs to be emphasised to candidates to accurately answer such questions in future. The concept of ‘quasi’ or ‘semi’ public goods is accepted but of course this still means that the private sector could provide them. Overall, marks were low and valid evaluation was rare. Section B Essays
A66: 9708_w21_22_Q2a | B66: 2021 | C66: Oct/Nov | D66: 9708/22 | E66: B | F66: 2 | G66: a | H66: One of 2, 3 or 4 | I66: 8 | J66: 0 | K66: Explain | M66: Yes | O66: diagram required | P66: 1.5 | Q66: Production possibility curves | R66: ;1.5;1.1; | S66: 1.5.1, 1.5.2, 1.1.3 | T66: PPC, opportunity cost, increasing opportunity cost | V66: Use a diagram(s) to explain how a production possibility curve can be used to show opportunity cost and why such a curve is usually drawn with increasing opportunity costs. | W66: For knowledge and understanding showing a diagram of a production possibility curve with correctly labelled axes (up to 2 marks) And application that explains how a movement along the curve illustrates opportunity cost. What opportunity cost is with reference to the products in the diagram(1), for showing a movement along the curve and the impacts on the output of the different products on the diagram (1) and explaining how this demonstrates opportunity cost (1) (up to 3 marks) And an explanation of why increasing opportunity costs are expected, curve must be concave and the significance explained (1), increasing opportunity costs clearly demonstrated on the diagram (1) and explained, e.g. because resources cannot be easily switched between products (1) (up to 3 marks) Guidance: Clearly the candidate only needs to draw one diagram to answer this question However, if the only diagram used shows a straight line PPC, then the maximum mark must be 5 as it cannot be used to answer the final part of the question Note: candidates may not follow the sequence described in this mark scheme, e.g. opportunity cost may be explained in the context of increasing opportunity cost, i.e. not separately. However, provided this is explained using a valid diagram, i.e. a concave PPC, then both marks must be awarded | X66: 10 | Y66: 4 | Z66: question paper | AD66: 9708_w22_22_Q3a (57%) | AE66: This was the least popular essay question probably due to the content of part (b). Most candidates were able to score at least half marks by drawing an accurate PPC diagram and demonstrating the concept of opportunity cost. However, the fact that this is demonstrated by a movement along the curve was rarely made clear and many candidates struggled to demonstrate the idea and cause of increasing opportunity cost and the significance of the concave shape of the curve.
A67: 9708_w21_22_Q2b | B67: 2021 | C67: Oct/Nov | D67: 9708/22 | E67: B | F67: 2 | G67: b | H67: One of 2, 3 or 4 | I67: 12 | J67: 4 | K67: Discuss | O67: absolute claim (always/only/alone) | P67: 6.1 | Q67: The reasons for international trade | R67: ;6.1; | S67: 6.1.1, 6.1.2 | T67: comparative advantage, free trade, limitations of the theory | V67: Discuss whether the principle of comparative advantage concludes that a movement to free trade will always result in an overall benefit for an economy. | W67: For analysis that explains how the principle of comparative advantage justifies free trade in terms of an increase in overall output/consumption possibilities that will benefit an economy/ies (up to 4 marks) For analysis that suggests why the shortcomings of the principle of comparative advantage might make it less useful and therefore free trade might not be beneficial for an economy/ies (up to 4 marks) 8 marks maximum For evaluative comment that assesses the relative strengths of each approach (up to 3 marks) And leads to a reasoned conclusion whether the principle of comparative advantage does suggest that a movement to free trade will always result in an overall benefit for an economy (1 mark) 4 marks maximum Guidance: The analysis here needs to show how free trade can lead to overall benefit for an economy but also that this might not be the case Several approaches are acceptable: some might argue that transport costs might negate the benefits of trade or that the exchange rate is not favourable. Others might argue that a movement to free trade might lead to structural adjustments that bring costs to the economy. Some might argue that as specialisation takes place resources are re-allocated and opportunity costs might rise Candidates may suggest reasons for protectionism as a counter argument – this is also acceptable Note: there are no KU marks awarded in part (b) for merely explaining/defining terms or phrases used within the question | X67: 11 | Y67: 4 | Z67: question paper | AE67: Answers to this question were generally not strong. Although most candidates had a vague grasp of the principle of comparative advantage and some spent a great deal of time drawing diagrams or preparing tables to show knowledge of the concept, very few used this knowledge to analyse whether a movement to free trade would benefit an economy. Some candidates omitted the principle from their discussion and answered a different question about the advantages and disadvantages of free trade. Marks were often very low and it re-emphasises the need to read the question carefully as in this case the focus was on using the principle of comparative advantage to analyse the benefits of free trade. Also, it provides a reminder that analysis and not simply knowledge gains the available marks in part b of essay questions.
A68: 9708_w21_22_Q3a | B68: 2021 | C68: Oct/Nov | D68: 9708/22 | E68: B | F68: 3 | G68: a | H68: One of 2, 3 or 4 | I68: 8 | J68: 0 | K68: Explain | M68: Yes | O68: diagram required | P68: 2.5 | Q68: Consumer and producer surplus | R68: ;2.5;3.2;2.2; | S68: 2.5.1, 2.5.3, 3.2.1 | T68: consumer surplus, indirect tax, PED | V68: Explain what is meant by consumer surplus and use diagrams to assess the impact on consumer surplus when an indirect tax is imposed on a good with price-elastic demand compared with the impact when the demand is price-inelastic. | W68: For knowledge and understanding of consumer surplus, the difference (1) between the price a consumer is willing to pay for a product and its market price/price actually paid (1) (up to 2 marks) And application using a diagram to show the impact of an indirect tax on the consumer surplus when the demand for a good is price-elastic. An accurately labelled diagram that clearly shows a flatter/elastic demand curve and the shift to the left of the supply curve (1), the impact on the price and quantity (1), and the fall in consumer surplus (1) (up to 3 marks) And application using a diagram to show the impact of an indirect tax on the consumer surplus when the demand for a good is price-inelastic. An accurately labelled diagram that clearly shows a steeper/inelastic demand curve and a shift to the left of the supply curve, and the impact on price and quantity (1). The impact on consumer surplus should be clearly shown and compared with that of a price-elastic good (1) and possible reasons for the difference, e.g. degree of substitutability, addictive nature of the good, etc. (1) (up to 3 marks) Guidance: The comparison could be reversed, i.e. the candidate may first consider the price- inelastic good with the price-elastic good. This should be equally rewarded | X68: 12 | Y68: 4 | Z68: question paper | AE68: A popular question that was well answered by most candidates who attempted it. Most candidates were able to accurately define consumer surplus although a significant number were unable to precisely define it as the difference between the price the consumer is prepared to pay and the price they do pay. Diagrams were generally accurate although in some cases more care needs to be taken to ensure they are clear and legible and of a reasonable size. The main issues were a tendency to reproduce pre-prepared answers to questions which are often set in this area, namely the impacts on both producer and consumer surplus and the different tax burdens. Although tax burden clearly has an impact on the size of the consumer surplus, it was not the question and nor was the impact on producer surplus. Candidates do need to answer the question that is set rather than one they may have prepared for. In a few cases, answers were completely undermined by drawing diagrams that showed a shift in the demand curve instead of or alongside a shift in the supply curve. Also, occasionally it was not possible to see any discernible difference between the slope of an elastic and an inelastic demand curve. Alongside the fact that the diagrams needed to show identical supply curves and supply curve shifts, it was sometimes difficult to identify or explain the different changes in consumer surplus,
A69: 9708_w21_22_Q3b | B69: 2021 | C69: Oct/Nov | D69: 9708/22 | E69: B | F69: 3 | G69: b | H69: One of 2, 3 or 4 | I69: 12 | J69: 4 | K69: Discuss | O69: compare two options | P69: 3.2 | Q69: Methods and effects of government intervention in markets | R69: ;3.2;3.3; | S69: 3.2.4, 3.2.2, 3.3.4 | T69: maximum price, food subsidies, food shortages | V69: A government is considering whether to adopt a policy of maximum price legislation in the market for food or to provide food subsidies to alleviate hunger in a period of food shortages. Discuss whether maximum price legislation or food subsidies are more likely to alleviate hunger under these circumstances. | W69: For analysis that explains the advantages and disadvantages of maximum price legislation (up to 4 marks) (3 marks maximum for an analysis that just considers either the advantages or the disadvantages) For analysis that explains the advantages and disadvantages of food subsidies (up to 4 marks) (3 marks maximum for an analysis that just considers either the advantages or the disadvantages) 8 marks maximum For evaluative comment that compares the relative strengths and weaknesses of each approach in alleviating hunger under these circumstances (up to 3 marks) And leads to a reasoned conclusion whether maximum price legislation or food subsidies are more likely to alleviate hunger under these circumstances (1 mark) 4 marks maximum Guidance: Maximum price legislation is imposed to keep the price of food low so that those on low incomes can afford to buy food. The impact, however, is to reduce the supply of food and create excess demand. Informal markets and queuing are likely to follow, and rationing might be necessary Food subsidies will reduce the price of food and increase the supply of food, but the impact depends upon the elasticity of demand of food. The effects might only be felt in the long term. The low prices might encourage hoarding of food. There are also possible opportunity costs involved as well as overall pressure on the government budget Subsidies may be ineffective in times of famine/supply chain crises, etc. Note: there are no KU marks awarded in part (b) for merely explaining/defining terms or phrases used within the question | X69: 13 | Y69: 4 | Z69: question paper | AE69: Most candidates were able to display accurate knowledge and understanding of maximum pricing and subsidies and there was little evidence of confusion with minimum pricing. However, the main issue was that whilst a great deal of effort went into explaining the mechanics of both policies alongside generally accurate diagrams, a significant number of candidates were less successful in applying this knowledge to the question i.e., how successful they may be in alleviating hunger in a period of food shortages. Therefore, good answers accurately used knowledge and understanding to analyse likely success and were able to make direct comparisons of strengths and weaknesses of the different policies within evaluation whereas weaker answers were descriptive, focused on knowledge and far less well applied to the question. Evaluation in the latter case was often summative and did not address the question. Candidates must recognise that knowledge and understanding is not analysis and that summaries do not represent evaluation unless focused on answering the question.
A70: 9708_w21_22_Q4a | B70: 2021 | C70: Oct/Nov | D70: 9708/22 | E70: B | F70: 4 | G70: a | H70: One of 2, 3 or 4 | I70: 8 | J70: 0 | K70: Explain | M70: Yes | O70: diagram required | P70: 4.6 | Q70: Price stability | R70: ;4.6;4.3; | S70: 4.6.1, 4.6.4, 4.3.12 | T70: inflation, demand-pull, cost-push, AD/AS | V70: Explain what is meant by inflation and, using diagrams, show how it can arise both as a result of a shift in the aggregate demand curve and a shift in the aggregate supply curve. | W70: For knowledge and understanding of inflation defined as a continuous/ sustained rise (1) in the general/average level of prices – a simple reference to price level is acceptable if it is clear from the rest of the answer that this refers to all prices and not just the price level of one product (1) (up to 2 marks) And application that uses a diagram to show that inflation can be caused by a shift to the right of the aggregate demand curve. For an explanation why AD might increase (1), an accurately labelled diagram that shows the rightwards shift in AD and resulting increase in the general price level (1), and clearly explains that inflation occurs due to this excess in aggregate demand (1) (up to 3 marks) And application that uses a diagram to show that inflation can be caused by a shift to the left of the aggregate supply curve. For an explanation why AS may fall (1), an accurately labelled diagram that shows the leftwards shift in AS and resulting increase in the general price level (1), and clearly explains that inflation occurs due to this decrease in aggregate supply (1) (up to 3 marks) Guidance: Do not reward ‘micro’ diagrams showing S/D or P/Q Axes should show general/average price level and output/GDP, etc. However, if it is clear from the written response that the candidate understands that it is an impact on general or average prices, then benefit of doubt can be given if the Y axis simply refers to P or prices and everything else on the diagram is accurate Reasons why AD may increase include a rise in C, I, G, X or a fall in M Reasons why AS may fall include a rise in costs, tax, etc. | X70: 14 | Y70: 4 | Z70: question paper | AE70: Question 4 was the most popular essay question and was generally answered well. The majority of candidates who attempted this question were able to accurately define inflation and produce diagrams showing the correct macro approach and were able to score between six and eight marks overall. The most common omissions were a lack of explanation that demand pull inflation results from an excess of aggregate demand over aggregate supply and that cost push inflation resulted from a fall in aggregate supply. Incorrectly labelled diagrams and explanations both showing a micro based approach were comparatively rare.
A71: 9708_w21_22_Q4b | B71: 2021 | C71: Oct/Nov | D71: 9708/22 | E71: B | F71: 4 | G71: b | H71: One of 2, 3 or 4 | I71: 12 | J71: 4 | K71: Discuss | P71: 4.6 | Q71: Price stability | R71: ;4.6; | S71: 4.6.5 | T71: consequences of inflation, domestic effects, external effects | V71: Discuss whether the domestic effects of inflation are more serious than the external effects for an economy. | W71: For analysis of the domestic effects of inflation (up to 4 marks) For analysis of the external effects of inflation (up to 4 marks) 8 marks maximum For evaluative comment that assesses the relative seriousness of the internal and external effects (up to 3 marks) And leads to a reasoned conclusion as to which effect is likely to be the most serious for an economy (1 mark) 4 marks maximum Guidance: The domestic effects include a haphazard redistribution of income, a fall in savings and productive investment, menu and shoe leather costs The external effects include a rise in the price of exports and a fall in the relative price of imports with implications for the current account of the balance of payments, the exchange rate and capital flows If any part of the answer confuses domestic effects with external effects, then this part should not be rewarded. However, parts that are accurate should be rewarded Note: there are no KU marks awarded in part (b) for merely explaining/defining terms or phrases used within the question | X71: 15 | Y71: 4 | Z71: question paper | AD71: 9708_w23_22_Q5b (85%), 9708_w24_23_Q4b (65%), 9708_w25_24_Q1d (60%) | AE71: Again, there were some very good answers, and most candidates were able to clearly and accurately distinguish between domestic and external effects. There were also some good attempts to evaluate their relative seriousness often in different scenarios, most commonly the degree of openness of the economies. Weaker answers either failed to distinguish effectively between domestic and external effects and/or simply asserted effects without explanation. For example, fiscal drag may well be an effect but without explanation it is simply knowledge and gains no credit. Some candidates also attempted to evaluate the general effects of inflation and/or the policies used to deal with inflation which of course was not the question and therefore could not be credited.
A72: 9708_w21_23_Q1a | B72: 2021 | C72: Oct/Nov | D72: 9708/23 | E72: A | F72: 1 | G72: a | I72: 2 | J72: 0 | K72: Describe | P72: 4.3 | Q72: AD and AS analysis | R72: ;4.3;4.4; | S72: 4.3.2, 4.4.2 | T72: components of AD, real output growth, data trend | U72: China – growth, consumption and the US trade war | V72: Use the data in Fig. 1.1 to describe how the contribution to real output growth of the different components of aggregate demand in China has changed from 2010 to 2017. | W72: Award 1 mark for any two of the following: • Lower contribution of investment expenditure over the period • Relatively stable contribution in consumption expenditure • In 2010, net exports were negative but by 2017 they were positive / however, over the period they have fluctuated between positive and negative (2 marks) Guidance: It is not enough to simply quote figures – some measure of change in contribution is needed, i.e. increase, decrease, no discernible change, etc. | X72: 6 | Y72: 3 | Z72: question paper | AA72: Chart needed: Fig. 1.1 is a bar chart with no printed values, so the source extract here cannot show it. Use the original paper. | AE72: Candidates do need to take note of the mark allocations when answering questions. As a two-mark question, there is no need for a great deal of writing and often two simple statements or a simple statement with some development is all that is required depending on the command word. This question involved simple data handling and simply asked for a description of changes in contribution of the different components of AD between two years. Consequently, there was no need to describe the changes year by year nor was there a need to describe the changes in real output growth. Two accurate changes over the period gained 2 marks and could have been obtained in two simple sentences.
A73: 9708_w21_23_Q1bi | B73: 2021 | C73: Oct/Nov | D73: 9708/23 | E73: A | F73: 1 | G73: b(i) | I73: 1 | J73: 0 | K73: Identify | P73: 2.2 | Q73: PED, YED and XED | R73: ;2.2;4.4; | S73: 2.2.3 | T73: YED, income and car sales | U73: China – growth, consumption and the US trade war | V73: What relationship might you expect between the rate of growth in real output and sales of new cars in an economy? | W73: There is likely to be a positive correlation / would be expected to be a similar pattern / trend between the rise in GDP growth and the change in private car sales (1 mark) | X73: 6 | Y73: 3 | Z73: question paper | AE73: As cars in general may be considered a normal good, as real output rises so would real income and therefore a positive correlation might be expected. Most candidates recognised this, but a lot of time was wasted in stating it through very lengthy explanations for only 1 mark. Some candidates attempted to reverse the statement i.e., a rise in output means more cars but this did not answer the question.
A74: 9708_w21_23_Q1bii | B74: 2021 | C74: Oct/Nov | D74: 9708/23 | E74: A | F74: 1 | G74: b(ii) | I74: 2 | J74: 0 | K74: Consider | P74: 2.2 | Q74: PED, YED and XED | R74: ;2.2;4.4; | S74: 2.2.3 | T74: data interpretation, car sales, real output growth | U74: China – growth, consumption and the US trade war | V74: Consider whether the evidence in Fig. 1.1 and Table 1.1 supports this relationship. | W74: It is broadly consistent (1) Highest and lowest rates of growth correspond (2010 and 2017 respectively) (1) There is positive growth in all years for both real output and sales of new cars, but rates of growth do not always match (1) Growth rate is more consistent than growth in car sales throughout (1) (2 marks) Guidance: 1 mark to be awarded for each accurate statement up to a maximum of 2 marks | X74: 6 | Y74: 3 | Z74: question paper | AA74: Chart needed: Fig. 1.1 is a bar chart with no printed values, so the source extract here cannot show it (Table 1.1 is included). Use the original paper. | AE74: Again 2 marks only here. Answers were often far too lengthy as the data suggests the relationship is broadly consistent which gained a mark with a piece of supporting evidence for the second mark. Consequently, a lot of unnecessary time was spent writing the answers to the first three questions which may have been better spent on the higher mark questions.
A75: 9708_w21_23_Q1c | B75: 2021 | C75: Oct/Nov | D75: 9708/23 | E75: A | F75: 1 | G75: c | I75: 3 | J75: 0 | K75: State | L75: Explain | P75: 6.2 | Q75: Protectionism | R75: ;6.2; | S75: 6.2.2, 6.2.3 | T75: tools of protection, trade war, consumers and producers | U75: China – growth, consumption and the US trade war | V75: State one protectionist measure that may be adopted by the US in a trade war with China and explain what effect this would have on consumers and producers in the US. | W75: Various possibilities including: • Tariff, quota, regulations (maximum of 1 mark for identifying one measure) • Increases prices of imported goods for consumers (1) and raises costs of production for producers due to higher imported raw material costs (1) increases demand for domestic producers (1) (3 marks) Guidance: Accept any other valid impacts on consumers and producers, but 1 mark max. for each and both must be considered for full marks | X75: 7 | Y75: 3 | Z75: question paper | AE75: This was probably the most accessible data response question and most candidates who attempted it were able to score full marks. Most were able to identify a relevant protectionist measure and apply it to show relevant impacts on both consumers and producers. There were very few weak answers that were unaware of what was meant by protectionist measures although a very small minority described measures that could be taken by China and not the USA which was irrelevant.
A76: 9708_w21_23_Q1d | B76: 2021 | C76: Oct/Nov | D76: 9708/23 | E76: A | F76: 1 | G76: d | I76: 6 | J76: 1 | K76: Discuss | P76: 5.2 | Q76: Fiscal policy | R76: ;5.2;2.2; | S76: 5.2.4, 2.2.3 | T76: direct tax cut, YED, normal and inferior goods | U76: China – growth, consumption and the US trade war | V76: Discuss whether cuts in direct taxes would increase the demand for all types of consumer goods in China. | W76: Award 1 mark for recognising that a cut in direct taxes may increase demand for consumer goods due to a rise in disposable income (1) Up to 2 marks for explanation of why a cut in direct taxes would increase demand for normal/luxury with a positive YED value consumer goods Up to 2 marks for an explanation of why a cut in direct taxes will not lead to an increase in demand for inferior/negative value consumer goods Up to a maximum mark of 5 for analysis Reserve 1 mark for a reasoned conclusion Guidance: Alternative ways of expressing disposable income are acceptable and should be rewarded, e.g. more spending power, more money in the pockets of consumers, etc. | X76: 7 | Y76: 3 | Z76: question paper | AE76: The quality of response was generally good. However, there was a significant minority who confused direct taxes with indirect taxes and therefore discussed the impact of PED rather than YED or simply assumed that demand for all goods would increase because of a fall in either direct or indirect taxes. Such answers gained 1 mark or 0 marks depending on whether they had accurately explained the rise in disposable income (1) by showing accurate knowledge of a fall in direct taxes or by a reference to a fall in prices (0) i.e., by confusing direct taxes with indirect taxes. For those who recognised the impact of YED and a reference to both normal and inferior goods plus a brief explanation of both, provided there was a brief conclusion then full marks were obtained. Those who scored less than full marks were often let down by references to normal and inferior goods with no explanations.
A77: 9708_w21_23_Q1e | B77: 2021 | C77: Oct/Nov | D77: 9708/23 | E77: A | F77: 1 | G77: e | I77: 6 | J77: 1 | K77: Discuss | O77: compare two options | P77: 4.4 | Q77: Economic growth | R77: ;4.4;4.3; | S77: 4.4.4, 4.3.5 | T77: consumption-led growth, investment, exports | U77: China – growth, consumption and the US trade war | V77: Discuss whether increasing domestic consumption is the best way for China to maintain the growth in real output at the current rate ‘over the next few years’. | W77: Analysis of the advantages and disadvantages of increasing domestic consumption to maintain the growth in real output (up to 3 marks) Max. 2 if only advantages or disadvantages are considered Analysis of the advantages and disadvantages of an alternative way/ ways, i.e. increased I or X (up to 3 marks). Max. 2 if only advantages or disadvantages are considered Up to a maximum mark of 5 for analysis Reserve 1 mark for a reasoned conclusion Guidance: Increasing domestic consumption will increase AD and output. This can be done through reducing direct or indirect taxes. The increased spending benefits the Chinese economy through increased employment and can be more certain than having to rely on external factors such as the global economy or US trade policy to generate growth. Care must be taken to not increase the rate of inflation as AD increases Alternative policies could be increasing investment or export-led growth | X77: 8 | Y77: 3 | Z77: question paper | AE77: Answers to this question were often quite weak. Many answers were descriptive rather than analytical and focused on how consumption may be increased rather than the benefits of doing so. Also, because the level of consumption had remained reasonably constant between 2010 and 2017, it was often assumed it could not be changed. On the other hand, net exports were regularly offered as an alternative as their contribution had increased over the same period but the impact of a trade war with the USA was ignored. Better answers compared the benefits of increasing consumption notably, the impact on employment and relative insulation from external factors against the possibility of inflationary pressure. This then allowed candidates to compare an alternative approach such as encouraging investment. Good evaluation was rare as analysis was often very limited. Section B Essays
A78: 9708_w21_23_Q2a | B78: 2021 | C78: Oct/Nov | D78: 9708/23 | E78: B | F78: 2 | G78: a | H78: One of 2, 3 or 4 | I78: 8 | J78: 0 | K78: Explain | P78: 1.1 | Q78: Scarcity, choice and opportunity cost | R78: ;1.1;1.4; | S78: 1.1.1, 1.1.4, 1.4.1 | T78: economic problem, planned economy, market economy | V78: Explain how the fundamental economic problem is addressed in a planned economy and in a market economy. | W78: For knowledge and understanding of fundamental economic problem, scarce resources (1) but unlimited wants (1) (up to 2 marks) And application that explains how this problem is addressed in a planned economy. Central planning, government allocation of resources, welfare, etc. may be discussed (up to 3 marks) And further application how this problem is addressed in a market economy. The role of the price mechanism, e.g. rationing, signalling, interaction of demand and supply, etc., may be discussed (up to 3 marks) Guidance: The fundamental economic problem is tackled by means of market forces in a market economy. In a planned economy it is in the hands of government to ensure that resource allocation is equitable and possible | X78: 9 | Y78: 4 | Z78: question paper | AE78: Most candidates were able to clearly and accurately define the fundamental economic problem to gain the two knowledge and understanding marks. A further two marks were also often gained through an explanation of the role of government in a planned economy and the role of the price mechanism in a market economy. However, answers were often vague and generalised beyond that, so it was comparatively rare to gain many more marks. Also, the command word was ‘explain’ so an evaluation of the benefits and drawbacks of each system was irrelevant, and a conclusion was unnecessary. Many candidates wasted a great deal of time assessing the relative merits of each system in general rather than answering the specific question which again highlights the need to read the question carefully.
A79: 9708_w21_23_Q2b | B79: 2021 | C79: Oct/Nov | D79: 9708/23 | E79: B | F79: 2 | G79: b | H79: One of 2, 3 or 4 | I79: 12 | J79: 4 | K79: Discuss | O79: absolute claim (always/only/alone) | P79: 1.6 | Q79: Classification of goods and services | R79: ;1.6;1.4;3.2; | S79: 1.6.2, 1.6.3, 1.4.1, 3.2.3 | T79: mixed economy, public goods, merit goods, role of government | V79: Discuss the view that in a mixed economy the only role of government should be to provide public goods and the supply of merit goods should be left to the private sector. | W79: Analysis of the reasons why public goods are provided by the government and not the private sector (up to 4 marks) Analysis of the reasons why merit goods may be provided by the private sector and/or the government (up to 4 marks) 8 marks maximum For an evaluation of whether the only role of government in a mixed economy is to provide public goods and that merit goods should be left to the private sector (up to 4 marks) Reserve 1 mark for a valid conclusion Guidance: Merit goods such as health provision, education and childcare are usually provided by both private and public sectors in a mixed economy. When provided by the private sector, a charge is usually but not always made at the point of use Government provision is funded through taxation; consumers will be charged a subsidised price or no charge at all. Much depends upon efficiency and how governments view the benefits of merit goods provision Without the involvement of government, some merit goods may be underprovided – may be used as an evaluative comment Note: there are no KU marks awarded in part (b) for merely explaining/defining terms or phrases used within the question | X79: 9 | Y79: 4 | Z79: question paper | AE79: This question was not answered particularly well and many candidates appeared to miss the point of the question about whether government should only provide public goods or whether there was also a role for them to provide merit goods. Partly this arose through a lack of precise understanding of what a public good is compared to a merit good and this often led to a generalised discussion of the role of government in a mixed economy. This meant that a large part of the answer was irrelevant or inaccurate and that knowledge was rarely successfully applied to analysing the scope of the question. Whilst knowledge must be accurate and relevant, it again needs to be emphasised that only appropriate analysis is credited in part (b) of essay questions. Consequently, relevant evaluation was rare.
A80: 9708_w21_23_Q3a | B80: 2021 | C80: Oct/Nov | D80: 9708/23 | E80: B | F80: 3 | G80: a | H80: One of 2, 3 or 4 | I80: 8 | J80: 0 | K80: Explain | P80: 2.2 | Q80: PED, YED and XED | R80: ;2.2; | S80: 2.2.6, 2.2.7 | T80: PED, proportion of income, total revenue | V80: Using the concept of price elasticity of demand, explain why increasing the price of the product is (i) a bad idea for a firm producing a product that constitutes a large proportion of household income, and (ii) a good idea for a firm producing a product that constitutes a small proportion of household income. | W80: For knowledge and understanding, meaning of PED (1) plus an accurate formula (1) (up to 2 marks) And application: For explanation of the effects on revenue where PED is elastic (i). For a product that constitutes a large proportion of household income this means that the PED will most likely be elastic (1) which means (1) so revenue is likely to fall (1) (up to 3 marks) For explanation of the effects on revenue where PED is inelastic (ii). For a product that constitutes a small proportion of household income this means that the PED is likely to be inelastic (1) which means (1) so revenue is likely to rise (1) (up to 3 marks) Guidance: Where PED is elastic, an increase in price will lead to less revenue A firm with an inelastic PED will experience an increase in its revenue if it increases the price of its product Note: simple explanations of the impact of elasticity should not be credited, e.g. an increase in price leads to a large fall in demand/no change in demand. The answer must refer to % or proportional changes | X80: 10 | Y80: 4 | Z80: question paper | AE80: Candidates are clearly well prepared for this type of question and there were many good answers despite the wording being different to those seen in the past. Most candidates applied their knowledge of the concept of elasticity precisely in terms of proportional or percentage responses rather than vague terms such as ‘no change’ or ‘large/small changes in demand’ Total marks between 6 and 8 were common. Weaker answers were those where knowledge and understanding was lacking or imprecise.
A81: 9708_w21_23_Q3b | B81: 2021 | C81: Oct/Nov | D81: 9708/23 | E81: B | F81: 3 | G81: b | H81: One of 2, 3 or 4 | I81: 12 | J81: 4 | K81: Discuss | O81: compare two options | P81: 2.2 | Q81: PED, YED and XED | R81: ;2.2; | S81: 2.2.8 | T81: XED, YED, pricing decisions | V81: Discuss whether cross elasticity of demand or income elasticity of demand is likely to be more useful in assisting a firm in its pricing decisions. | W81: For an analysis of price changes on the market for substitutes and complements (up to 4 marks but a max. of 3 if only complements or substitutes are considered) For an analysis of price changes on normal/luxury goods and inferior goods when incomes change (up to 4 marks but a max. of 3 if only normal/luxury or inferior goods are considered) 8 marks maximum For an evaluation of which of the two measures is likely to be most useful to the firm in its pricing decisions (up to 4 marks) Reserve 1 mark for a conclusion Guidance: XED and YED should only be analysed in the context of their usefulness in assisting a firm in its pricing decisions Note: there are no KU marks awarded in part (b) for merely explaining/defining terms or phrases used within the question | X81: 11 | Y81: 4 | Z81: question paper | AD81: 9708_w22_21_Q2b (64%), 9708_w23_21_Q2b (73%), 9708_m24_22_Q3b (60%), 9708_s24_23_Q2b (58%), 9708_s26_24_Q2b (67%) | AE81: As is often common with questions of this nature, candidates displayed a great deal of knowledge and understanding of the two types of elasticity but did not apply this to answering the question. Also, because of the reference to pricing decisions in the question, there was occasional confusion with PED. Better answers limited their explanations of YED and XED and focused on how useful they may be to firms in deciding on prices in different situations whereas weaker answers focused on explaining/defining the different measures. For all part (b) answers, only relevant analysis is credited along with evaluation that is clearly drawn on this analysis and used to answer the question i.e., in this instance, which measure is likely to be the most useful.
A82: 9708_w21_23_Q4a | B82: 2021 | C82: Oct/Nov | D82: 9708/23 | E82: B | F82: 4 | G82: a | H82: One of 2, 3 or 4 | I82: 8 | J82: 0 | K82: Explain | P82: 4.6 | Q82: Price stability | R82: ;4.6; | S82: 4.6.2, 4.6.5 | T82: measuring inflation, CPI, consequences of inflation | V82: Explain how inflation is measured and why a rising rate of inflation may be of concern to consumers and producers. | W82: For knowledge and understanding of what is meant by inflation and how it is measured. Inflation is a sustained increase in the (general) price level (1) and is normally measured by the CPI or equivalent index (1) (up to 2 marks) And application that explains the problems for consumers (e.g. loss of purchasing power if on fixed income, erosion of real value of savings). 1 mark per explained problem (up to 3 marks) And further application that explains the problems for producers (e.g. menu costs, difficulty in making long-term decisions such as investment). 1 mark per explained problem (up to 3 marks) Guidance: Inflation occurs when there is a rise in the general price level in an economy. It is usually measured by the annual change in a Consumer Prices Index (CPI). A rising rate of inflation is of concern depending on its extent and how this compares with any stated target Reference to fixed income earners, menu costs, shoe leather costs, export competitiveness and business confidence are relevant At least two problems for each should be explained and one problem well explained can gain 2 marks. | X82: 11 | Y82: 4 | Z82: question paper | AE82: Part (a) questions allocate two marks for knowledge and understanding and a further six marks for applying this knowledge and understanding. There were two marks here for knowledge of what inflation is and how it is measured plus three marks for explaining why a rising rate of inflation may be of concern to consumers and a further three marks for the effect on producers. Many candidates concentrated on the mechanics of how inflation is measured and described the whole process with little regard to the impact required by the question and therefore scored low marks. Better responses quickly defined inflation and normally referred to CPI followed up by relevant application and in these instances, scored well, often achieving full marks. Once again, the advice is to spend less time displaying knowledge and understanding and more on applying or analysing this knowledge as required by the question.
A83: 9708_w21_23_Q4b | B83: 2021 | C83: Oct/Nov | D83: 9708/23 | E83: B | F83: 4 | G83: b | H83: One of 2, 3 or 4 | I83: 12 | J83: 4 | K83: Discuss | O83: compare two options | P83: 5.3 | Q83: Monetary policy | R83: ;5.3;4.6;5.2; | S83: 5.3.4, 4.6.4 | T83: interest rates, inflation control, alternative policies | V83: Discuss whether a policy of increasing interest rates is the best way of controlling a rising rate of inflation in an economy. | W83: For analysis of the advantages and disadvantages of a policy of increasing interest rates to control inflation. (Up to 4 marks but 3 marks max. if only advantages or disadvantages are considered) For analysis of the advantages and disadvantages of at least one other policy used to control inflation. (Up to 4 marks but 3 marks max. if only advantages or disadvantages are considered) 8 marks maximum For an evaluation as to which is likely to be the best policy to control inflation (up to 4 marks) Reserve 1 mark for a valid conclusion Guidance: There are various policies for controlling a rising rate of inflation, one of which is increasing interest rates. This policy is expected to reduce consumption and investment by firms whilst increasing savings. The effectiveness though depends upon the rate of inflation and the time it takes for increased interest rates to have an impact. Fiscal and supply-side policies are alternative methods of control Note: there are no KU marks awarded in part (b) for merely explaining/defining terms or phrases used within the question | X83: 12 | Y83: 4 | Z83: question paper | AD83: 9708_s22_23_Q3b (56%), 9708_s23_22_Q5b (63%) | AE83: Most candidates had a reasonable understanding of the use of interest rates to control a rising rate of inflation and better candidates were able to consider the negative impacts on growth and therefore were easily able to compare the use of supply side policy. However, many candidates simply stated how interest rates might control inflation alongside other policies without really comparing their effectiveness. The overall effect was to provide an answer which simply listed methods of controlling inflation. Consequently, effective evaluation was extremely rare. Once again, this emphasises the need to address the question and use appropriate analysis rather than simply listing knowledge and understanding.
A84: 9708_m22_22_Q1a | B84: 2022 | C84: Feb/March | D84: 9708/22 | E84: A | F84: 1 | G84: a | I84: 2 | J84: 0 | K84: Describe | P84: 6.3 | Q84: Current account of the balance of payments | R84: ;6.3; | S84: 6.3.2 | T84: current account balance, data trend | U84: Turkey – current account, inflation and interest rate cuts | V84: With reference to Fig 1.1 describe how Turkey’s current account balance has changed between August 2019 and April 2020. | W84: It has gone/changed/moved from a surplus (1 mark) to a deficit (1 mark) Guidance: This is the only appropriate answer. Do not reward references to positive and / or negative figures / worsening etc. Equally, chronological descriptions of each year should not be credited even if references to surplus and/ or deficit are made throughout. The only exception is if it is clear that the candidate recognises the correct change over the time period e. g as a summative comment. | X84: 6 | Y84: 3 | Z84: question paper | AD84: 9708_s21_21_Q1ai (59%) | AE84: The focus of this question was the change between August 2019 and April 2020 and the simple answer was that the current account balance had changed from a surplus to a deficit. This was all that was required for 2 marks and detailed descriptions of all the changes in the balance within that time period were irrelevant. Candidates are also required to use the correct terminology, i.e., surplus and deficit and not use terms such as positive and negative (which are evident from the figures) or use value judgements such as ‘worsened’. Unfortunately, in many responses, far too much time was taken up with unnecessary description.
A85: 9708_m22_22_Q1b | B85: 2022 | C85: Feb/March | D85: 9708/22 | E85: A | F85: 1 | G85: b | I85: 2 | J85: 0 | K85: Explain | P85: 6.1 | Q85: The reasons for international trade | R85: ;6.1; | S85: 6.1.3 | T85: terms of trade, export and import prices, data interpretation | U85: Turkey – current account, inflation and interest rate cuts | V85: How could the data in Fig 1.2 be used to explain the changes in the terms of trade between August 2019 and April 2020 as shown in Fig 1.3? | W85: The rate of inflation in Turkey suggests that there is a rise in Turkey’s export prices (1 mark), if import prices will rise by less this will lead to a rise in the terms of trade as shown (1 mark) Guidance: The data clearly shows that prices have risen consistently over the time period and that terms of trade have risen from a value of 103.47 to 110.32. | X85: 6 | Y85: 3 | Z85: question paper | AE85: A significant number of candidates continue to confuse ‘Terms of Trade’ with ‘Balance of Trade’ even when the correct formula is reproduced. This misunderstanding was also compounded in many cases with a suggestion that a fall in the rate of inflation meant that prices would fall. Consequently, a number of candidates made the incorrect assertion that Terms of Trade improved because export prices had become more competitive. Those who did understand that inflation had led to a rise in the index of export prices gained one mark but often failed to receive the second mark by recognising that Terms of Trade would only have been improved if the index of import prices did not increase by the same percentage.
A86: 9708_m22_22_Q1c | B86: 2022 | C86: Feb/March | D86: 9708/22 | E86: A | F86: 1 | G86: c | I86: 4 | J86: 0 | K86: Explain | P86: 6.3 | Q86: Current account of the balance of payments | R86: ;6.3;2.2;4.6; | S86: 6.3.4, 2.2.7, 4.6.5 | T86: inflation, international competitiveness, PED for exports and imports, current account | U86: Turkey – current account, inflation and interest rate cuts | V86: ‘Consumer price inflation was 8.6% per annum in October 2019 and is now 11.4%, reducing the international competitiveness of Turkey’s goods and services.’ Explain, using the concept of price elasticity of demand, how the increase in inflation has caused the change in Turkey’s current account of the balance of payments between October 2019 and April 2020 as shown in Fig 1.1. | W86: Clear understanding of PED either by means of a formula or explanation based on % changes or responsiveness (1 mark) Recognition that the data (TOT) shows that export prices have increased more than import prices and an explanation of how the value of PED will affect export revenue (1 mark) and import expenditure respectively (1 mark) For reference to the Marshall-Lerner condition needing to be fulfilled to turn the current account surplus to a deficit (1 mark) Guidance: It is necessary for candidates to have a sound grasp of the core concepts especially the terms of trade, PED, and the Marshall-Lerner condition. The change from a surplus to a deficit will only occur if the Marshall-Lerner condition is fulfilled. The understanding of PED may be implicit based on the explanations of how the value of PED will affect export revenue and import expenditure and the first mark can therefore be awarded. If the answer only considers the impact on export revenue OR import expenditure, then a maximum of 2 marks may be awarded. | X86: 7 | Y86: 3 | Z86: question paper | AE86: This question required candidates to use the concept of price elasticity of demand to explain why consumer price inflation in Turkey had led to the current account moving into deficit. Most candidates were able to offer a definition and/or the formula for PED but a many of those were unable to clearly apply the concept to answer the question. Common errors involved a vague application of the concept, e.g., elastic PED means demand changes a lot when price changes or simply ignoring PED and instead stating that demand falls when price rises, Candidates should be reminded that PED measures degrees of responsiveness and this needs to be explained more clearly. Even those who correctly explained elasticity and understood that an elastic PED would mean that a price rise for exports would lead to a larger percentage fall in demand for exports tended to discuss this in terms of export volume rather than export revenue as used in the measurement of the current account. The impact on import expenditure was rarely referred to along with the need for the Marshall Lerner condition to be fulfilled to cause the change from surplus to deficit. Consequently, marks for this question were often very low.
A87: 9708_m22_22_Q1di | B87: 2022 | C87: Feb/March | D87: 9708/22 | E87: A | F87: 1 | G87: d(i) | I87: 3 | J87: 0 | K87: Explain | P87: 5.3 | Q87: Monetary policy | R87: ;5.3;4.6; | S87: 4.6.3 | T87: functions of money, standard of deferred payment, real interest rate | U87: Turkey – current account, inflation and interest rate cuts | V87: Explain how a negative real rate of interest in Turkey will affect the function of money as: a standard of deferred payment. | W87: for explaining what is meant by a ‘standard of deferred payment’ (1 mark) for explaining how this function of money will be affected by negative rates of interest i.e. who might be affected e.g., borrowers (1 mark) and how e.g., they will pay back less than they borrowed in real terms (1 mark) (Up to 2 marks) Guidance: If interest rates are negative, it means that borrowers will pay back less than they have borrowed in real terms. | X87: 7 | Y87: 3 | Z87: question paper | AA87: Functions of money: not in the 2023+ AS syllabus (now A Level). | AE87: It was apparent that most candidates did not have clear knowledge of what a standard of deferred payment meant and consequently, marks for this question were generally low. Some candidates referred to the redistribution between lenders and borrowers because of inflation without any link to this function of money and some referred to the exchange rate in their answer which was clearly not relevant.
A88: 9708_m22_22_Q1dii | B88: 2022 | C88: Feb/March | D88: 9708/22 | E88: A | F88: 1 | G88: d(ii) | I88: 3 | J88: 0 | K88: Explain | P88: 5.3 | Q88: Monetary policy | R88: ;5.3;4.6; | S88: 4.6.3 | T88: functions of money, store of value, real interest rate | U88: Turkey – current account, inflation and interest rate cuts | V88: Explain how a negative real rate of interest in Turkey will affect the function of money as: a store of value. | W88: for explaining what is meant by a ‘store of value’. (1 mark) for explaining how this function of money will be affected by negative rates of interest i.e. who might be affected e.g., savers (1 mark) and how e.g., the value of their savings would be reduced in real terms (1 mark) (Up to 2 marks) Guidance: If interest rates are negative, it means that savings are losing value in real terms. | X88: 8 | Y88: 3 | Z88: question paper | AA88: Functions of money: not in the 2023+ AS syllabus (now A Level). | AE88: This part was answered more convincingly although some candidates confused store of value with unit of account. Most knew that savers were affected although the impact on borrowers and consumers was also referred to which adversely affected the overall level of understanding. Marks awarded though were higher for this part of the question.
A89: 9708_m22_22_Q1e | B89: 2022 | C89: Feb/March | D89: 9708/22 | E89: A | F89: 1 | G89: e | I89: 6 | J89: 2 | K89: Discuss | M89: Yes | O89: compare two options; diagram required | P89: 5.3 | Q89: Monetary policy | R89: ;5.3;4.3;4.6; | S89: 5.3.4, 4.3.12 | T89: interest rate cut, aggregate demand, inflation, economic recovery | U89: Turkey – current account, inflation and interest rate cuts | V89: Discuss, with the help of an aggregate demand and aggregate supply diagram, whether further cuts in Turkey’s interest rate are likely to ‘generate inflation’ or ‘speed up the economic recovery’. | W89: For an accurate aggregate demand/aggregate supply diagram showing equilibrium national income and price level (1 mark). For an explanation using the diagram (1 mark) of the impact of a cut in interest rates upon aggregate demand (up to 2 marks). For evaluative comment that considers whether the interest rate cut will impact upon prices/employment/economic growth. (Up to 2 marks) with 1 mark reserved for a valid conclusion Guidance: Cuts in the rate of interest are expected to increase consumption and investment. In addition, the exchange rate will fall causing a rise in net exports. Aggregate demand will rise, but the impact upon prices and output and employment will be determined by the position of equilibrium national income. If there is no diagram or an inaccurate diagram, then the maximum mark is 4 i.e. 0,2,2. | X89: 8 | Y89: 3 | Z89: question paper | AE89: This question produced some good answers and low marks were often the result of assertions without explanation and/or inaccurate AS/AD diagrams. To gain marks, accurately labelled diagrams (i.e., price level, GDP, output etc but not P/Q on the axes, with AS and AD clearly shown along with relevant equilibrium positions) were needed. Explanations as to why AD would increase and how this would generate economic recovery were also needed. The counter argument was whether inflation would also be generated, and this is clearly a result of AS which needed to be explained. It was not sufficient to merely read off a new price level on a simple SRAS/AD diagram and assert that inflation would occur without any explanation. A considered conclusion was required for the final mark. Many candidates received 4+ marks out of 6. Section B Essay questions
A90: 9708_m22_22_Q2a | B90: 2022 | C90: Feb/March | D90: 9708/22 | E90: B | F90: 2 | G90: a | H90: One of 2, 3 or 4 | I90: 8 | J90: 0 | K90: Explain | M90: Yes | O90: diagram required | P90: 1.5 | Q90: Production possibility curves | R90: ;1.5;1.1; | S90: 1.5.1, 1.5.3, 1.1.3 | T90: PPC, capital vs consumer goods, short run vs long run | V90: Explain with the help of a production possibility curve diagram(s) how a decision to re-allocate resources in an economy to produce more capital goods and fewer consumer goods would affect consumers in both the short run and the long run. | W90: For knowledge and understanding of production possibility curves showing an accurate diagram labelled consumer goods and capital goods or equivalent (up to 2 marks). For application showing a movement along the curve in the short run (1 mark) meaning fewer consumer goods and services available for consumption (1 mark) leading to less choice / higher prices / lower living standards in the short run (1 mark). For application showing an outward shift of the curve in the long run (1 mark) perhaps leading to more consumer goods and services due to an expansion of capacity in the economy (1 mark) and an increase in living standards etc (1 mark). Guidance: The PPC diagram should show consumer goods and capital goods on the axes. These terms do not have to be used, but it must be clear that the candidate understands the distinction between the two. The significance of the reallocation should be clearly understood. In the short run the consumer will have less goods and services available to consume. In the long run there may be a shift outward in the PPC as more capital goods are produced and the economy’s capacity expands. An accurate diagram must include accurate labels with the PPC touching both axes. | X90: 9 | Y90: 4 | Z90: question paper | AE90: This was a popular question, and most candidates were able to explain the short run impact on consumers using an accurate production possibility curve and the identification of a movement along the curve itself. The long run impact was less well explained and many simply asserted that more goods would be produced rather than using a production possibility curve to show the likely outward shift in the curve. As a result, marks of 4 or 5 maximum were quite common. Some candidates persist in labelling the diagram axes as P and Q and/or do not draw the curve touching both axes. Other common errors showed an outward swivel of the curve to show the short run reallocation of resources rather than a movement along the curve and there were many answers that included irrelevant analysis of opportunity cost, descriptions of attainable, unattainable and points within the curve etc. Clearly, these have been the focus of previous questions but not this one and demonstrates the dangers of pre-prepared answers.
A91: 9708_m22_22_Q2b | B91: 2022 | C91: Feb/March | D91: 9708/22 | E91: B | F91: 2 | G91: b | H91: One of 2, 3 or 4 | I91: 12 | J91: 4 | K91: Discuss | O91: absolute claim (always/only/alone) | P91: 1.4 | Q91: Resource allocation in different economic systems | R91: ;1.4; | S91: 1.4.1, 1.4.2 | T91: planned economy, market economy, transition, consumers | V91: Discuss whether the transition from a planned economy to a market economy will always benefit consumers. | W91: For analysis of the potentially positive consequences of the transition for consumers OR the advantages and disadvantages to consumers of a planned economy. For an analysis of just one (3 max). (Up to 4 marks) For analysis of the potentially negative consequences of the transition for consumers OR the advantages and disadvantages to consumers of a market economy. For an analysis of just one (3 max). (Up to 4 marks) 8 marks maximum For evaluation that considers the ‘will always’ element of the question. (Up to 3 marks) to arrive at a reasoned conclusion. (1 mark) Guidance: The transition to a market economy will represent a movement towards consumer sovereignty. If there is imperfect information however there will be an underproduction of merit goods and an overproduction of demerit goods. Candidates are required to consider the advantages and disadvantages of a market economy and then to exercise some judgement about whether the transition will always be better for consumers. Reverse arguments should not be rewarded twice. | X91: 10 | Y91: 4 | Z91: question paper | AD91: 9708_w21_21_Q2b (75%) | AE91: This part of the question was answered reasonably well, and most candidates were able to discuss some of the key advantages to consumers of a transition from a planned economy to a market economy and by implication, the disadvantages of a planned economy. Likewise, the disadvantages of the transition were also reasonably well discussed. The most common weaknesses that persist were a lack of explanation and too much assertion. This often meant that genuine evaluation was lacking as it consisted mainly of a summary of the various conclusions rather than an attempt to evaluate the question of whether the transition will always be better for consumers. Some candidates did examine the impact on the domestic and external economy in general and occasionally discussed the benefits of a mixed economy, neither of which addressed the question set and therefore scored low marks.
A92: 9708_m22_22_Q3a | B92: 2022 | C92: Feb/March | D92: 9708/22 | E92: B | F92: 3 | G92: a | H92: One of 2, 3 or 4 | I92: 8 | J92: 0 | K92: Explain | P92: 2.3 | Q92: Price elasticity of supply | R92: ;2.3; | S92: 2.3.4 | T92: PES, determinants of PES, examples | V92: Use examples to explain why the supply of some products is price elastic and the supply of other products is price inelastic. | W92: For knowledge and understanding of what is meant by price elasticity of supply. What it measures (1 mark) and the formula (1 mark). For application that uses valid example(s) to explain price elastic supply (1 mark) identifies a factor that makes the supply of the product price elastic (1 mark) and why (1 mark) explanation of a factor that influences the elasticity. (Up to 3 marks) For application that uses valid example(s) to explain price inelastic supply (1 mark) identifies a factor that makes the supply of the product price inelastic (1 mark) and why (1 mark) explanation of a factor that influences the elasticity. (Up to 3 marks) Guidance: For full marks there must be an explanation of at least two factors that influence elasticity. If the candidate considers only one factor and reverses this factor, then 1 maximum for the second application. For example, if a candidate suggests that a product is elastic in supply because there are plentiful resources and then reverses this to explain that price might be inelastic because of a shortage of resources, this can only be credited once. | X92: 11 | Y92: 4 | Z92: question paper | AD92: 9708_w24_21_Q2b (56%) | AE92: Most candidates were able to correctly define price elasticity of supply and then went on to consider possible factors that could influence PES, such as the availability of resources, the number of producers, the extent of spare capacity, the ease of storing stocks, the time period, the extent of factor mobility and the length of the production process, giving appropriate examples of products with an elastic and an inelastic PES. A few candidates failed to understand that the question was concerned with the price elasticity of supply and wrote about the price elasticity of demand instead. Occasionally, as with all discussions of elasticity, a degree of imprecision persists despite an accurate definition, i.e., elastic is often discussed as a big change and inelastic as a small change or even no change. This suggests a learned definition but a lack of real understanding when applying the concept in a question such as this.
A93: 9708_m22_22_Q3b | B93: 2022 | C93: Feb/March | D93: 9708/22 | E93: B | F93: 3 | G93: b | H93: One of 2, 3 or 4 | I93: 12 | J93: 4 | K93: Discuss | L93: Consider | P93: 5.2 | Q93: Fiscal policy | R93: ;5.2;5.4; | S93: 5.2.4, 5.2.5, 5.4.3 | T93: fiscal policy, aggregate supply, supply-side effects of fiscal policy | V93: Discuss the ways in which fiscal policy can be used to increase the aggregate supply of products in an economy and consider whether this approach is likely to be effective. | W93: For analysis that considers how changes in taxation can influence aggregate supply with reference to the difficulties associated with this approach. For an analysis of how changes in taxation might work without the possible difficulties (3 max). (Up to 4 marks) For analysis that considers how changes in government spending can influence aggregate supply with reference to the difficulties associated with this approach. For an analysis of how changes in government spending might work without the possible difficulties (3 max). (Up to 4 marks) 8 marks maximum For evaluation that fully assesses the effectiveness of these approaches in increasing aggregate supply of products in an economy (up to 3 marks) and arrives at a reasoned conclusion concerning whether fiscal policy is likely to be effective. (1 mark) Guidance: Cuts in income and business taxes may provide incentives and increase the supply of labour and entrepreneurship to the economy. The difficulty is that they might not stimulate these resources. In addition, this could lead to a budget deficit and possible inflation. Increases in government spending could be directed to improving labour skills. Subsidies would also be included in this category encouraging for e.g., investment in R & D. This could also lead to a budget deficit and may take some time before this comes to fruition. A comparison of fiscal policy with another policy may be relevant within the evaluation but is not relevant analysis. | X93: 11 | Y93: 4 | Z93: question paper | AE93: The wording of this question was slightly unusual in that it was asking candidates to consider the uses of fiscal policy in stimulating aggregate supply and not, as is most common, aggregate demand. Nor was the question asking candidates to compare the use of fiscal policy with the use of supply side policy or monetary policy although this could form part of the conclusion. Many candidates did recognise this and there were some good responses with reasonable evaluation. However, a significant number did focus purely on aggregate demand and tried to redress this, unconvincingly by suggesting that AS would simply increase in line with AD which once again suggests a pre prepared response to a different question. Such answers tended to gain credit only insofar as they made a direct link to AS (normally in the context of government spending on training and education) and inevitably gained no evaluation marks in assessing the overall effectiveness of fiscal policies in increasing AS.
A94: 9708_m22_22_Q4a | B94: 2022 | C94: Feb/March | D94: 9708/22 | E94: B | F94: 4 | G94: a | H94: One of 2, 3 or 4 | I94: 8 | J94: 0 | K94: Explain | L94: Describe | P94: 6.2 | Q94: Protectionism | R94: ;6.2; | S94: 6.2.1, 6.2.2 | T94: protectionism, tools of protection, steel industry | V94: An economy is facing the shutdown of its steel making industry as a result of cheap imports. Explain what is meant by ‘protectionism’ and describe two ways in which this steel industry could be protected. | W94: For knowledge and understanding of the meaning of protection in terms of giving an advantage to domestic industries/protecting domestic industries against foreign competition (1 mark) through interference with the free market / restricting free trade / increasing the price competitiveness of domestic industries against foreign competition. (1 mark) For application that illustrates how industries are protected. Identification of a method (1 mark) and an explanation of how the chosen method works in practice (1 mark) and develops how this bestows advantage on the domestic industry. (1 mark) (Up to 3 marks) 2 methods × 3 marks: 6 maximum Guidance: Candidates should not be credited for simply stating that protectionism is ‘protecting industries’. There must be a developed reference to foreign competition. Accept any valid method of protection for e.g., tariffs, export subsidies, quotas etc. | X94: 12 | Y94: 4 | Z94: question paper | AE94: Clear understanding of the term protectionism was rare. Most candidates were able to refer to the fact that it offered an advantage for domestic industries / protected them against foreign competition but very few added that this was done by interference with the free market / trade. The most common methods applied were tariffs and quotas although embargoes and red tapism were also referred to. Weaknesses lay in incomplete application of how the methods actually worked and how they gave an advantage to domestic industry by interfering with the free market and/or restricting free trade. One method frequently quoted was the use of subsidies which often received little or no credit as the candidate failed to say they would in fact be export subsidies. Consequently, there was a wide range of marks although full marks were rare due to the frequent imprecision of the definition.
A95: 9708_m22_22_Q4b | B95: 2022 | C95: Feb/March | D95: 9708/22 | E95: B | F95: 4 | G95: b | H95: One of 2, 3 or 4 | I95: 12 | J95: 4 | K95: Discuss | L95: Consider | P95: 6.2 | Q95: Protectionism | R95: ;6.2; | S95: 6.2.3 | T95: protectionism, strategic industry, retaliation, consumers | V95: Discuss the advantages and disadvantages of protecting an industry such as steel and consider whether the protection will be of overall benefit to this economy. | W95: For analysis of the advantages of protecting the industry. (up to 4 marks) For analysis of the disadvantages of protecting the industry. (up to 4 marks) 8 marks maximum For evaluation that considers the relative effect of the advantages and disadvantages of protection (Up to 3 marks) to arrive at a reasoned conclusion on the overall benefit to the economy. (1 mark) Guidance: Advantages include, the infant industry argument, anti-dumping and protecting employment. Disadvantages include the fact that resources may not be allocated in their most efficient use, there might be retaliation and consumers will have to pay higher prices. Overall benefit should be fully considered for evaluation marks. | X95: 12 | Y95: 4 | Z95: question paper | AE95: This part of the question was generally well answered, with candidates discussing the potential advantages of protection, such as in relation to the need to protect infant and declining industries, the need to protect employment and the need for protection against firms who were dumping products at a price below cost, and the potential disadvantages of protection, such as an inefficient allocation of resources, higher prices, and the possibility of retaliation. However, weaker candidates tended to offer lists without any explanation which did lead to some low marks. Unfortunately, relatively few candidates responded to the reference to ‘overall benefit’ at the end of the question and instead merely summarised the analysis. This meant that marks for evaluation were often very low.
A96: 9708_s22_21_Q1a | B96: 2022 | C96: May/June | D96: 9708/21 | E96: A | F96: 1 | G96: a | I96: 2 | J96: 0 | K96: Describe | P96: 4.6 | Q96: Price stability | R96: ;4.6; | S96: 4.6.2 | T96: inflation trend, data trend | U96: Bangladesh – inflation | V96: Describe the trend in the annual inflation rate of Bangladesh between 2009 and 2019. | W96: Although the inflation rate is virtually the same in 2009 and 2019, the trend has been up and down during this period, i.e., the trend is fluctuating. (1 mark) Within this overall trend, it rose between 2009 and 2011 and then fell between 2012 and 2019, although within those years it both rose and fell. (1 mark) The inflation rate was not lower than 5.4% in any of the years between 2009 and 2019 but was significantly higher in four of the years: 11.4% in 2011, 8.1% in 2010, 7.5% in 2013 and 7.0% in 2014. (1 mark) 2 marks maximum Guidance: No mark to be given to answers that just state the eleven figures without any recognition of the overall trend. | X96: 6 | Y96: 3 | Z96: question paper | AD96: 9708_w24_21_Q1a (56%) | AE96: Many candidates were able to correctly describe the overall trend in the annual inflation rate of Bangladesh between 2009 and 2019, stressing that although the inflation rate was approximately the same at the beginning and at the end of the period, it had generally fluctuated during this time, reaching its highest rate of 11.4 in 2011. Some candidates, however, gave a description of what happened in every year. It is important that candidates understand clearly what is meant by a ‘trend’.
A97: 9708_s22_21_Q1b | B97: 2022 | C97: May/June | D97: 9708/21 | E97: A | F97: 1 | G97: b | I97: 2 | J97: 0 | K97: Explain | P97: 4.6 | Q97: Price stability | R97: ;4.6; | S97: 4.6.2 | T97: consumer price index, weights | U97: Bangladesh – inflation | V97: Explain why price changes in the food and the non-food sectors in Bangladesh are treated differently when calculating the CPI. | W97: A basic recognition that price changes in the food and the non-food sectors in Bangladesh may be different, possibly including some appropriate examples (1 mark) A clear recognition of the importance of weights in the construction of a CPI/a specific reference to, and explanation of, weightings in the calculation of the CPI for a country. There needs to be a clear reference to weights/weightings by a candidate to award the second mark (1 mark) Guidance: Bangladesh: There have been significant price rises in the food sector, including: • vegetables, particularly onions • fish • chicken There have also been significant price rises in the non-food sector, including: • healthcare • transport • energy resources such as gas Weighting: • the situation where certain products are given larger weights to reflect the greater proportion of income spent on them takes into account the relative importance of the components of a CPI | X97: 7 | Y97: 3 | Z97: question paper | AE97: A number of candidates were able to explain why price changes in the food and non-food sectors in Bangladesh were treated differently when calculating the Consumer Price Index, stressing the different weights that were given to various sectors according to the proportion of income spent on them and therefore their relative importance in the pattern of expenditure.
A98: 9708_s22_21_Q1c | B98: 2022 | C98: May/June | D98: 9708/21 | E98: A | F98: 1 | G98: c | I98: 4 | J98: 0 | K98: Explain | P98: 4.6 | Q98: Price stability | R98: ;4.6; | S98: 4.6.5 | T98: consequences of inflation, international competitiveness | U98: Bangladesh – inflation | V98: Explain one domestic consequence and one external consequence for Bangladesh of having ‘a relatively high rate of inflation’. | W98: For an identification of one possible domestic consequence. (1 mark) For an explanation of one possible domestic consequence. (1 mark) For an identification of one possible external consequence (1 mark) For an explanation of one possible external consequence (1 mark) Guidance: The domestic consequences for Bangladesh of a relatively high rate of inflation could include: • redistribution of income as the real earnings of some workers in Bangladesh rise and the real earnings of others in Bangladesh fall • borrowers in Bangladesh will gain and lenders in Bangladesh will lose • menu costs in Bangladesh, e.g., the cost of changing prices • shoe leather costs in Bangladesh, e.g., the search for good returns • greater uncertainty – could discourage investment in Bangladesh • purchasing power of money for people in Bangladesh weaker The external consequences for Bangladesh of a relatively high rate of inflation could include: • if the rate of inflation in Bangladesh is higher than in other countries (it states it is one of the highest in Asia), this will make the country’s exports less competitive (the effect will depend on PED) • this may worsen the current account position of Bangladesh. | X98: 8 | Y98: 3 | Z98: question paper | AE98: Many candidates were able to explain one domestic consequence and one external consequence for Bangladesh of having ‘a relatively high rate of inflation’. Domestic consequences included the redistribution of income, the impact on borrowers and lenders and the existence of menu and shoe leather costs. External consequences included the impact of the rate of inflation on the competitiveness of exports and the effect of this on the current account of the balance of payments. However, some candidates did not appear to understand the difference between ‘domestic’ and ‘external’ consequences.
A99: 9708_s22_21_Q1d | B99: 2022 | C99: May/June | D99: 9708/21 | E99: A | F99: 1 | G99: d | I99: 6 | J99: 0 | K99: Analyse | M99: Yes | O99: diagram required | P99: 4.6 | Q99: Price stability | R99: ;4.6;4.3; | S99: 4.6.4, 4.3.12 | T99: demand-pull inflation, cost-push inflation, wages, AD/AS | U99: Bangladesh – inflation | V99: Analyse, with the help of aggregate demand and aggregate supply diagrams, how increasing wages can cause both demand-pull and cost-push inflation in Bangladesh. | W99: For an analysis of demand-pull inflation in relation to wage increases. (1 mark) For an AD/AS diagram to show demand-pull inflation. (Up to 2 marks) 1 mark for correct labelling of the diagram 1 mark for the shift to the right of AD, showing increase in price level For an analysis of cost-push inflation in relation to wage increases. (1 mark) For an AD/AS diagram to show cost-push inflation. (Up to 2 marks) 1 mark for correct labelling of the diagram 1 mark for the shift to the left of AS, showing increase in price level Guidance: Demand-pull inflation: • it is stated that there has been an annual increase in the Wage Rate Index (WRI) of 6.6% in the last month of 2019 • increased consumer spending, e.g., through greater consumer confidence resulting from an increase in income • the AD curve will shift to the right causing an increase in the general price level Cost-push inflation: • wage increases to employees that are not linked to higher productivity • the AS curve will shift to the left causing an increase in the general price level The diagrams need to be accurately labelled, with the vertical axis labelled ‘general price level’ or ‘price level’ and the horizontal axis labelled ‘real output’ or ‘real GDP’. | X99: 9 | Y99: 3 | Z99: question paper | AD99: 9708_s24_22_Q1b (65%) | AE99: The majority of candidates were able to analyse how increasing wages could cause both demand- pull and cost-push inflation in Bangladesh, distinguishing clearly between the two types of inflation. Although many candidates gained full marks for the diagrams, some provided demand and supply diagrams rather than AD and AS diagrams and some labelled the axes incorrectly, labelling the vertical axis ‘price’ instead of ‘price level’ and the horizontal axis ‘quantity’ rather than ‘real GDP’. Some candidates did not include any diagrams in their answers, despite the explicit instruction in the question to do so.
A100: 9708_s22_21_Q1e | B100: 2022 | C100: May/June | D100: 9708/21 | E100: A | F100: 1 | G100: e | I100: 6 | J100: 1 | K100: Discuss | O100: absolute claim (always/only/alone); compare two options | P100: 5.3 | Q100: Monetary policy | R100: ;5.3;5.2;4.6; | S100: 5.3.4, 5.2.7 | T100: monetary policy, fiscal policy, inflation control | U100: Bangladesh – inflation | V100: ‘However, there is always the possibility that tough monetary policies could do more harm than good to an economy, compared with the possible use of fiscal policy.’ Discuss whether monetary policy or fiscal policy is more likely to be effective in controlling inflation. | W100: For an explanation of the potential advantages and potential disadvantages of monetary policy in controlling inflation. (Up to 3 marks) (A maximum of 2 marks if only advantages or disadvantages are explained) For an explanation of the potential advantages and potential disadvantages of fiscal policy in controlling inflation. (Up to 3 marks) (A maximum of 2 marks if only advantages or disadvantages are explained) 5 marks maximum Reserve 1 mark for a conclusion Guidance: Potential advantages of monetary policy: • a rise in interest rates can be effective in reducing the level of aggregate demand, especially if demand is interest-elastic; can be effective reducing demand-pull inflation • other monetary policies to control inflation can include a reduction of the money supply and a rise in the exchange rate Potential disadvantages of monetary policy: • an increase in interest rates may not be significant enough to have an effect, i.e., demand is relatively inelastic • the impact of an increase in interest rates can take a relatively long time to take effect • it will be less useful in controlling cost-push inflation • a rise in the exchange rate will not be useful if the PED for imports and exports is inelastic • a reduction of the money supply may sometimes be difficult to bring about Potential advantages of fiscal policy: • a reduction in public expenditure can help to reduce the level of aggregate demand in an economy • an increase in the level of taxes can also have such an effect Potential disadvantages of fiscal policy: • it may not always be easy for a government to change its expenditure/revenue plans • increased taxes can have a disincentive effect • less useful controlling cost-push inflation | X100: 10 | Y100: 3 | Z100: question paper | AE100: A number of candidates made a good attempt to discuss whether monetary policy or fiscal policy was more likely to be effective in controlling inflation, although some candidates limited themselves to a general description of monetary policy and fiscal policy rather than focusing on which would be more likely to be effective in controlling inflation. However, a number of candidates did not offer a conclusion, even though it was a ‘discuss’ question.
...

Sheet Topic Matrix
A1: How often each AS topic appears (count of question parts tagged with it)
A2: Columns read variant/series/year, e.g. 23/O/N/25 = 9708/23 Oct/Nov 2025. Counts any tag (primary or secondary). "Marks as primary" sums marks where the topic is the main focus. Updates automatically as rows are added to Questions.
A4: Code | B4: Topic | C4: 22/F/M/21 | D4: 21/M/J/21 | E4: 22/M/J/21 | F4: 23/M/J/21 | G4: 21/O/N/21 | H4: 22/O/N/21 | I4: 23/O/N/21 | J4: 22/F/M/22 | K4: 21/M/J/22 | L4: 22/M/J/22 | M4: 23/M/J/22 | N4: 21/O/N/22 | O4: 22/O/N/22 | P4: 23/O/N/22 | Q4: 22/F/M/23 | R4: 21/M/J/23 | S4: 22/M/J/23 | T4: 23/M/J/23 | U4: 21/O/N/23 | V4: 22/O/N/23 | W4: 23/O/N/23 | X4: 22/F/M/24 | Y4: 21/M/J/24 | Z4: 22/M/J/24 | AA4: 23/M/J/24 | AB4: 21/O/N/24 | AC4: 22/O/N/24 | AD4: 23/O/N/24 | AE4: 21/M/J/25 | AF4: 22/M/J/25 | AG4: 23/M/J/25 | AH4: 24/M/J/25 | AI4: 21/O/N/25 | AJ4: 22/O/N/25 | AK4: 23/O/N/25 | AL4: 24/O/N/25 | AM4: 21/M/J/26 | AN4: 22/M/J/26 | AO4: 23/M/J/26 | AP4: 24/M/J/26 | AQ4: Total parts | AR4: As primary | AS4: Marks as primary
A5: 1.1 | B5: Scarcity, choice and opportunity cost | C5: =COUNTIFS(Questions!$R$2:$R$1000,"*;"&$A5&";*",Questions!$B$2:$B$1000,2021,Questions!$C$2:$C$1000,"Feb/March",Questions!$D$2:$D$1000,"9708/22") -> 0 | D5: =COUNTIFS(Questions!$R$2:$R$1000,"*;"&$A5&";*",Questions!$B$2:$B$1000,2021,Questions!$C$2:$C$1000,"May/June",Questions!$D$2:$D$1000,"9708/21") -> 0 | E5: =COUNTIFS(Questions!$R$2:$R$1000,"*;"&$A5&";*",Questions!$B$2:$B$1000,2021,Questions!$C$2:$C$1000,"May/June",Questions!$D$2:$D$1000,"9708/22") -> 0 | F5: =COUNTIFS(Questions!$R$2:$R$1000,"*;"&$A5&";*",Questions!$B$2:$B$1000,2021,Questions!$C$2:$C$1000,"May/June",Questions!$D$2:$D$1000,"9708/23") -> 1 | G5: =COUNTIFS(Questions!$R$2:$R$1000,"*;"&$A5&";*",Questions!$B$2:$B$1000,2021,Questions!$C$2:$C$1000,"Oct/Nov",Questions!$D$2:$D$1000,"9708/21") -> 0 | H5: =COUNTIFS(Questions!$R$2:$R$1000,"*;"&$A5&";*",Questions!$B$2:$B$1000,2021,Questions!$C$2:$C$1000,"Oct/Nov",Questions!$D$2:$D$1000,"9708/22") -> 1 | I5: =COUNTIFS(Questions!$R$2:$R$1000,"*;"&$A5&";*",Questions!$B$2:$B$1000,2021,Questions!$C$2:$C$1000,"Oct/Nov",Questions!$D$2:$D$1000,"9708/23") -> 1 | J5: =COUNTIFS(Questions!$R$2:$R$1000,"*;"&$A5&";*",Questions!$B$2:$B$1000,2022,Questions!$C$2:$C$1000,"Feb/March",Questions!$D$2:$D$1000,"9708/22") -> 1 | K5: =COUNTIFS(Questions!$R$2:$R$1000,"*;"&$A5&";*",Questions!$B$2:$B$1000,2022,Questions!$C$2:$C$1000,"May/June",Questions!$D$2:$D$1000,"9708/21") -> 0 | L5: =COUNTIFS(Questions!$R$2:$R$1000,"*;"&$A5&";*",Questions!$B$2:$B$1000,2022,Questions!$C$2:$C$1000,"May/June",Questions!$D$2:$D$1000,"9708/22") -> 0 | M5: =COUNTIFS(Questions!$R$2:$R$1000,"*;"&$A5&";*",Questions!$B$2:$B$1000,2022,Questions!$C$2:$C$1000,"May/June",Questions!$D$2:$D$1000,"9708/23") -> 1 | N5: =COUNTIFS(Questions!$R$2:$R$1000,"*;"&$A5&";*",Questions!$B$2:$B$1000,2022,Questions!$C$2:$C$1000,"Oct/Nov",Questions!$D$2:$D$1000,"9708/21") -> 0 | O5: =COUNTIFS(Questions!$R$2:$R$1000,"*;"&$A5&";*",Questions!$B$2:$B$1000,2022,Questions!$C$2:$C$1000,"Oct/Nov",Questions!$D$2:$D$1000,"9708/22") -> 1 | P5: =COUNTIFS(Questions!$R$2:$R$1000,"*;"&$A5&";*",Questions!$B$2:$B$1000,2022,Questions!$C$2:$C$1000,"Oct/Nov",Questions!$D$2:$D$1000,"9708/23") -> 2 | Q5: =COUNTIFS(Questions!$R$2:$R$1000,"*;"&$A5&";*",Questions!$B$2:$B$1000,2023,Questions!$C$2:$C$1000,"Feb/March",Questions!$D$2:$D$1000,"9708/22") -> 0 | R5: =COUNTIFS(Questions!$R$2:$R$1000,"*;"&$A5&";*",Questions!$B$2:$B$1000,2023,Questions!$C$2:$C$1000,"May/June",Questions!$D$2:$D$1000,"9708/21") -> 0 | S5: =COUNTIFS(Questions!$R$2:$R$1000,"*;"&$A5&";*",Questions!$B$2:$B$1000,2023,Questions!$C$2:$C$1000,"May/June",Questions!$D$2:$D$1000,"9708/22") -> 0 | T5: =COUNTIFS(Questions!$R$2:$R$1000,"*;"&$A5&";*",Questions!$B$2:$B$1000,2023,Questions!$C$2:$C$1000,"May/June",Questions!$D$2:$D$1000,"9708/23") -> 0 | U5: =COUNTIFS(Questions!$R$2:$R$1000,"*;"&$A5&";*",Questions!$B$2:$B$1000,2023,Questions!$C$2:$C$1000,"Oct/Nov",Questions!$D$2:$D$1000,"9708/21") -> 0 | V5: =COUNTIFS(Questions!$R$2:$R$1000,"*;"&$A5&";*",Questions!$B$2:$B$1000,2023,Questions!$C$2:$C$1000,"Oct/Nov",Questions!$D$2:$D$1000,"9708/22") -> 0 | W5: =COUNTIFS(Questions!$R$2:$R$1000,"*;"&$A5&";*",Questions!$B$2:$B$1000,2023,Questions!$C$2:$C$1000,"Oct/Nov",Questions!$D$2:$D$1000,"9708/23") -> 0 | X5: =COUNTIFS(Questions!$R$2:$R$1000,"*;"&$A5&";*",Questions!$B$2:$B$1000,2024,Questions!$C$2:$C$1000,"Feb/March",Questions!$D$2:$D$1000,"9708/22") -> 0 | Y5: =COUNTIFS(Questions!$R$2:$R$1000,"*;"&$A5&";*",Questions!$B$2:$B$1000,2024,Questions!$C$2:$C$1000,"May/June",Questions!$D$2:$D$1000,"9708/21") -> 0 | Z5: =COUNTIFS(Questions!$R$2:$R$1000,"*;"&$A5&";*",Questions!$B$2:$B$1000,2024,Questions!$C$2:$C$1000,"May/June",Questions!$D$2:$D$1000,"9708/22") -> 0 | AA5: =COUNTIFS(Questions!$R$2:$R$1000,"*;"&$A5&";*",Questions!$B$2:$B$1000,2024,Questions!$C$2:$C$1000,"May/June",Questions!$D$2:$D$1000,"9708/23") -> 0 | AB5: =COUNTIFS(Questions!$R$2:$R$1000,"*;"&$A5&";*",Questions!$B$2:$B$1000,2024,Questions!$C$2:$C$1000,"Oct/Nov",Questions!$D$2:$D$1000,"9708/21") -> 0 | AC5: =COUNTIFS(Questions!$R$2:$R$1000,"*;"&$A5&";*",Questions!$B$2:$B$1000,2024,Questions!$C$2:$C$1000,"Oct/Nov",Questions!$D$2:$D$1000,"9708/22") -> 2 | AD5: =COUNTIFS(Questions!$R$2:$R$1000,"*;"&$A5&";*",Questions!$B$2:$B$1000,2024,Questions!$C$2:$C$1000,"Oct/Nov",Questions!$D$2:$D$1000,"9708/23") -> 0 | AE5: =COUNTIFS(Questions!$R$2:$R$1000,"*;"&$A5&";*",Questions!$B$2:$B$1000,2025,Questions!$C$2:$C$1000,"May/June",Questions!$D$2:$D$1000,"9708/21") -> 1 | AF5: =COUNTIFS(Questions!$R$2:$R$1000,"*;"&$A5&";*",Questions!$B$2:$B$1000,2025,Questions!$C$2:$C$1000,"May/June",Questions!$D$2:$D$1000,"9708/22") -> 0 | AG5: =COUNTIFS(Questions!$R$2:$R$1000,"*;"&$A5&";*",Questions!$B$2:$B$1000,2025,Questions!$C$2:$C$1000,"May/June",Questions!$D$2:$D$1000,"9708/23") -> 1 | AH5: =COUNTIFS(Questions!$R$2:$R$1000,"*;"&$A5&";*",Questions!$B$2:$B$1000,2025,Questions!$C$2:$C$1000,"May/June",Questions!$D$2:$D$1000,"9708/24") -> 0 | AI5: =COUNTIFS(Questions!$R$2:$R$1000,"*;"&$A5&";*",Questions!$B$2:$B$1000,2025,Questions!$C$2:$C$1000,"Oct/Nov",Questions!$D$2:$D$1000,"9708/21") -> 2 | AJ5: =COUNTIFS(Questions!$R$2:$R$1000,"*;"&$A5&";*",Questions!$B$2:$B$1000,2025,Questions!$C$2:$C$1000,"Oct/Nov",Questions!$D$2:$D$1000,"9708/22") -> 1 | AK5: =COUNTIFS(Questions!$R$2:$R$1000,"*;"&$A5&";*",Questions!$B$2:$B$1000,2025,Questions!$C$2:$C$1000,"Oct/Nov",Questions!$D$2:$D$1000,"9708/23") -> 1 | AL5: =COUNTIFS(Questions!$R$2:$R$1000,"*;"&$A5&";*",Questions!$B$2:$B$1000,2025,Questions!$C$2:$C$1000,"Oct/Nov",Questions!$D$2:$D$1000,"9708/24") -> 0 | AM5: =COUNTIFS(Questions!$R$2:$R$1000,"*;"&$A5&";*",Questions!$B$2:$B$1000,2026,Questions!$C$2:$C$1000,"May/June",Questions!$D$2:$D$1000,"9708/21") -> 0 | AN5: =COUNTIFS(Questions!$R$2:$R$1000,"*;"&$A5&";*",Questions!$B$2:$B$1000,2026,Questions!$C$2:$C$1000,"May/June",Questions!$D$2:$D$1000,"9708/22") -> 0 | AO5: =COUNTIFS(Questions!$R$2:$R$1000,"*;"&$A5&";*",Questions!$B$2:$B$1000,2026,Questions!$C$2:$C$1000,"May/June",Questions!$D$2:$D$1000,"9708/23") -> 0 | AP5: =COUNTIFS(Questions!$R$2:$R$1000,"*;"&$A5&";*",Questions!$B$2:$B$1000,2026,Questions!$C$2:$C$1000,"May/June",Questions!$D$2:$D$1000,"9708/24") -> 0 | AQ5: =SUM(C5:AP5) -> 16 | AR5: =COUNTIF(Questions!$P$2:$P$1000,$A5) -> 5 | AS5: =SUMIF(Questions!$P$2:$P$1000,$A5,Questions!$I$2:$I$1000) -> 16
